Workbook
Name lstRegion: Lists!$A$1:$A$5
Name lstChannel: Lists!$B$1:$B$4
Name lstCategory: Lists!$C$1:$C$5
Name lstYesNo: Lists!$D$1:$D$2
Name pLateDays: Parameters!$C$5
Name pLowMargin: Parameters!$C$6
Name pHighCutoff: Parameters!$C$8
Name pRegion: Dashboard!$C$5
Name pChannel: Dashboard!$E$5
Name pCategory: Dashboard!$G$5
Name pIncludeCancelled: Dashboard!$I$5
Name pStart: Dashboard!$K$5
Name pEnd: Dashboard!$M$5

Sheet Cover
A1: Harbor & Co. advanced data analysis
A2: Excel pipeline · extract, clean, analyze, dashboard, test
B4: Objective
B5: Turn a dirty order extract into a decision-ready sales view: what sold, where, through which channel, and which orders are late, returned, or thin on margin.
B8: Pipeline
B9: 1. Raw_Data holds the dirty extract. 2. pipeline/clean.py standardizes aliases, dates, numbers, duplicates, and invalid rows. 3. Cleaned_Data stores the surviving orders. Revenue, margin, and flags are Excel formulas. 4. Chart_Data and Dashboard aggregate with SUMIFS / COUNTIFS / AVERAGEIFS so filters recalculate in Excel. 5. QA_Tests checks those formulas against the values locked by the Python run.
B13: Default window
B14: 2024-01-01 to 2025-09-30. Cancelled orders are excluded from sales KPIs. Seed 42. Raw rows 1,649. Clean rows 1,618.
B16: Headline result
B17: Net revenue $2,220,660 · Orders 1,558 · AOV $1,425 · Gross margin 29.4% · Return rate 7.1% · On time 75.5%.
B19: How to use the dashboard
B20: Open Dashboard. Pick Region, Channel, Category, the cancelled switch, and the date window. Excel recalculates the KPI cards and all ten charts. Comparison charts keep their breakdown: the region chart does not collapse when you pick one region.

Sheet Lists
A1: All | B1: All | C1: All | D1: Yes
A2: North | B2: Store | C2: Furniture | D2: No
A3: South | B3: Online | C3: Lighting
A4: East | B4: Wholesale | C4: Textiles
A5: West | C5: Kitchen

Sheet Parameters
A1: Model parameters
A2: Dashboard dropdowns are the filters. Thresholds below drive late-shipment and margin flags.
B4: Parameter | C4: Value | D4: What it controls | E4: Limitation
B5: Late shipment threshold (days) | C5: 7 | D5: LateFlag and the on-time KPI. Edit this cell and Excel recalculates. | E5: Does not rewrite history; it only changes the cutoff.
B6: Low-margin threshold | C6: 0.15 | D6: Low-margin KPI. Stored as a fraction (0.15 = 15%). | E6: Compared with each order's margin, not the weighted regional margin.
B7: High-value percentile | C7: 0.9 | D7: Documented percentile used when the pipeline computed the cutoff. | E7: Changing this cell does not recompute the cutoff. Rerun the pipeline.
B8: High-value cutoff | C8: 3064.63 | D8: HighValueFlag. Orders at or above this net revenue count as high value. | E8: Cutoff is fixed for the saved parameter set and the All/All/All filter. Dropdowns do not rebuild the percentile.
B9: Random seed | C9: 42 | D9: Makes the synthetic extract reproducible. | E9: The extract is synthetic. It is not a client ledger.
B10: Include cancelled (echo) | C10: =pIncludeCancelled | D10: Mirrors the dashboard switch. | E10: Yes includes cancelled orders in sales KPIs. Return rate and on-time still exclude them.
B11: Analysis start (echo) | C11: =pStart | D11: Mirrors the dashboard date. | E11: Rows outside the window stay on Cleaned_Data and drop out of every SUMIFS.
B12: Analysis end (echo) | C12: =pEnd | D12: Mirrors the dashboard date. | E12: Same window rule as the start date.

Sheet Raw_Data
A1: OrderID | B1: OrderDate | C1: Region | D1: Channel | E1: Category | F1: Product | G1: Segment | H1: Quantity | I1: UnitPrice | J1: Discount | K1: UnitCost | L1: ShipDays | M1: Status | N1: SalesRep
A2: HC-100000 | B2: 05/21/2025 | C2: West | D2: Online | E2: Furniture | F2: Linen Sofa | G2: Consumer | H2: 2 | I2: $1,307.21 | J2: 0.14 | K2: 862.76 | L2: 4 | M2: Completed | N2: J. Patel
A3: HC-100001 | B3: 03-Sep-24 | C3: West | D3: Online | E3: Furniture | F3: Lounge Chair | G3: Home Office | H3: 2 | I3: 453.45 | J3: 0.03 | K3: 272.07 | L3: 10 | M3: Completed | N3: R. Ibarra
A4: HC-100002 | B4: 2025/03/04 | C4: West | D4: Online | E4: Lighting | F4: Arc Lamp | G4: Corporate | H4: 3 | I4: 292.13 | J4: 0.13 | K4: 140.22 | L4: 6 | M4: Completed | N4: L. Berger
A5: HC-100003 | B5: 18.05.2025 | C5: Eas | D5: Online | E5: FURNITURE | F5: Walnut Shelf | G5: Consumer | H5: 2 | I5: 188.96 | J5: 0.09 | K5: 103.93 | L5: 6 | M5: Completed | N5: A. Shah
A6: HC-100004 | B6: 03/09/2024 | C6: West | D6: web | E6: Furniture | F6: Lounge Chair | G6: Consumer | H6: 2 | I6: 495.08 | J6: 0.04 | K6: 297.05 | L6: 5 | M6: complete | N6: P. Rossi
A7: HC-100005 | B7: 30-Jul-24 | C7: North | D7: Wholesale | E7: Lighting | F7: Brass Sconce | G7: Corporate | H7: 13 | I7: 141.77 | J7: 18% | K7: 65.22 | L7: 3 | M7: Completed | N7: R. Ibarra
A8: HC-100006 | B8: 2024/04/22 | C8: North | D8: web | E8: Furniture | F8: Linen Sofa | G8: Home Office | H8: 3 | I8: 1219.37 | J8: 0.11 | K8: 804.79 | L8: 5 | M8: Completed | N8: R. Ibarra
A9: HC-100007 | B9: 09.10.2024 | C9: West | D9: B2B | E9: Furniture | F9: Oak Desk | H9: 16 | I9: 863.15 | J9: 0.14 | K9: 535.15 | L9: 6 | M9: Completed | N9: S. Nguyen
A10: HC-100008 | B10: 08/29/2024 | C10: West | D10: Store | E10: Lighting | F10: Brass Sconce | G10: Home Office | H10: 2 | I10: 132.49 | J10: 0.11 | K10: 60.94 | L10: 3 | M10: Completed | N10: M. Okonkwo
A11: HC-100009 | B11: 28-Jul-24 | C11: West | D11: Store | E11: Furniture | F11: Oak Desk | H11: 4 | I11: 796.89 | J11: 0.02 | K11: 494.07 | L11: 3 | M11: COMPLETED | N11: J. Patel
A12: HC-100010 | B12: 2025/03/24 | C12: North | D12: Online | E12: Textiles | F12: Cotton Duvet | G12: Consumer | H12: one | I12: 112.78 | J12: 0.04 | K12: 49.62 | L12: 5 | M12: Returned | N12: P. Rossi
A13: HC-100011 | B13: 05.09.2025 | C13: West | D13: Online | E13: Lighting | F13: Pendant Light | G13: Consumer | H13: 2 | I13: 168.74 | J13: 0.02 | K13: 84.37 | L13: 4 | M13: Completed | N13: K. Mensah
A14: HC-100012 | B14: 06/09/2024 | C14: West | D14: Online | E14: Furniture | F14: Oak Desk | G14: consumer | H14: 3 | I14: 792.45 | J14: 12% | K14: 491.32 | L14: 4 | M14: complete | N14: A. Shah
A15: HC-100013 | B15: 25-Sep-24 | C15: South | D15: Wholesale | E15: Kitchen | F15: Ceramic Set | G15: consumer | H15: 23 | I15: 82.38 | J15: 0.16 | K15: 31.30 | L15: 9 | M15: complete | N15: A. Shah
A16: HC-100014 | B16: 2025/09/10 | C16: West | D16: Online | E16: Textiles | F16: Linen Curtain | G16: Consumer | H16: 3 | I16: 95.22 | J16: 0.11 | K16: 42.85 | L16: 1 | M16: RETURNED | N16: M. Okonkwo
A17: HC-100015 | B17: 15.07.2024 | C17: WEST | D17: Wholesale | E17: Lighting | F17: Brass Sconce | G17: Consumer | H17: 17 | I17: 147.81 | J17: 0.23 | K17: 67.99 | L17: 7 | M17: Completed | N17: K. Mensah
A18: HC-100016 | B18: 03/17/2024 | C18: north | D18: B2B | E18: Kitchen | F18: Cast Skillet | G18: Consumer | H18: 19 | I18: 56.55 | J18: 0.28 | K18: 22.62 | L18: 6 | M18: Returned | N18: S. Nguyen
A19: HC-100017 | B19: 05-Dec-24 | C19: North | D19: Store | E19: Furniture | F19: Lounge Chair | G19: Home Office | H19: 3 | I19: 501.07 | J19: 0.05 | K19: 300.64 | L19: 8 | M19: Completed | N19: P. Rossi
A20: HC-100018 | B20: 2024/12/30 | C20: west | D20: Online | E20: Lighting | F20: Brass Sconce | G20: Corporate | H20: 3 | I20: 150.11 | J20: 0.13 | K20: 69.05 | L20: 10 | M20: Compleated | N20: J. Patel
A21: HC-100019 | B21: 17.05.2025 | C21: West | D21: Wholesale | E21: FURNITURE | F21: Oak Desk | G21: Consumer | H21: 29 | I21: 907.08 | J21: 0.14 | K21: 562.39 | L21: 6 | M21: Completed | N21: K. Mensah
A22: HC-100020 | B22: 02/24/2024 | C22: west | D22: Store | E22: Kitchen | F22: Chef Knife | G22: Corporate | H22: 1 | I22: 68.38 | J22: 0.10 | K22: 24.62 | L22: 8 | M22: Completed | N22: A. Shah
A23: HC-100021 | B23: 17-Mar-25 | C23: East | D23: Store | E23: Textiles | F23: Linen Curtain | G23: Consumer | H23: 1 | I23: 88.37 | J23: 0.11 | K23: 39.77 | L23: 7 | M23: Completed | N23: A. Shah
... A31: HC-100029 | B31: 05-Sep-25 | C31: West | D31: Online | E31: Lighting | F31: Arc Lamp | G31: Consumer | H31: 1 | I31: 323.76 | J31: 0.03 | K31: 155.40 | L31: 7 | M31: Completed | N31: A. Shah
A32: HC-100030 | B32: 2024/02/11 | C32: East | D32: e-commerce | E32: Textiles | F32: Wool Throw | H32: 1 | I32: 70.75 | J32: 0.14 | K32: 29.71 | L32: 7 | M32: Completed | N32: K. Mensah
A33: HC-100031 | B33: 16.08.2024 | C33: West | D33: Store | E33: Textiles | F33: Cotton Duvet | G33: Consumer | H33: 2 | I33: 127.42 | J33: 0.03 | K33: 56.07 | L33: 7 | M33: Completed | N33: R. Ibarra
A34: HC-100032 | B34: 08/23/2025 | C34: South | D34: Store | E34: Lighting | F34: Arc Lamp | G34: Consumer | H34: 1 | I34: 286.08 | J34: 0.02 | K34: 137.32 | L34: 6 | M34: Completed | N34: R. Ibarra
A35: HC-100033 | B35: 14-Dec-24 | C35: East | D35: Store | E35: Furniture | F35: Linen Sofa | G35: Corporate | H35: 3 | I35: 1192.38 | J35: 0.02 | K35: 786.97 | L35: 9 | M35: Completed | N35: S. Nguyen
A36: HC-100034 | B36: 2025/02/22 | C36: West | D36: Online | E36: Lighting | F36: Arc Lamp | G36: Consumer | H36: 1 | I36: 290.31 | J36: 0.17 | K36: 139.35 | L36: 1 | M36: complete | N36: J. Patel
A37: HC-100035 | B37: 05.10.2024 | C37: NORTH | D37: Wholesale | E37: Furniture | F37: Oak Desk | G37: Corporate | H37: 11 | I37: 817.57 | J37: 22% | K37: 506.89 | L37: 5 | M37: Completed | N37: S. Nguyen
A38: HC-100036 | B38: 04/10/2024 | C38: North | D38: Store | E38: Kitchen | F38: Ceramic Set | G38: Consumer | H38: 1 | I38: 79.55 | J38: 0.02 | K38: 30.23 | L38: 1 | M38: Compleated | N38: A. Shah
A39: HC-100037 | B39: 30-Nov-24 | C39: west | D39: Store | E39: Kitchen | F39: Chef Knife | G39: Consumer | H39: 2 | I39: 65.03 | J39: 0.10 | K39: 23.41 | L39: 7 | M39: Completed | N39: L. Berger
A40: HC-100038 | B40: 2024/04/24 | C40: East | D40: Store | E40: Lighting | F40: Arc Lamp | G40: Consumer | H40: 1 | I40: 257.42 | J40: 0.00 | K40: 123.56 | L40: 10 | M40: Cancelled | N40: J. Patel
A41: HC-100039 | B41: 02.01.2024 | C41: North | D41: Wholesale | E41: FURNITURE | F41: Walnut Shelf | G41: consumer | H41: 25 | I41: 216.35 | J41: 0.23 | K41: 118.99 | L41: 8 | M41: Completed | N41: S. Nguyen
A42: HC-100040 | B42: 07/21/2025 | C42: East | D42: Store | E42: Kitchen | F42: Chef Knife | G42: Consumer | H42: 2 | I42: 60.91 | J42: 0.02 | K42: 21.93 | L42: 6 | M42: Completed | N42: M. Okonkwo
A43: HC-100041 | B43: 27-Jul-25 | C43: North | D43: Store | E43: Textiles | F43: Linen Curtain | G43: Consumer | H43: 2 | I43: 93.13 | J43: 0.12 | K43: 41.91 | L43: 5 | M43: Completed | N43: A. Shah
A44: HC-100042 | B44: 2024/04/10 | C44: east | D44: Store | E44: Kitchen | F44: Ceramic Set | G44: Consumer | H44: 3 | I44: 80.54 | J44: 0.01 | K44: 30.60 | L44: 7 | M44: Completed | N44: M. Okonkwo
... A55: HC-100053 | B55: 13-Feb-25 | C55: West | D55: In-Store | E55: Lighting | F55: Arc Lamp | G55: Home Office | H55: 3 | I55: $319.23 | J55: 0.06 | K55: 153.23 | L55: 4 | M55: Completed | N55: S. Nguyen
A56: HC-100054 | B56: 2025/06/22 | C56: West | D56: Store | E56: Furniture | F56: Oak Desk | H56: 3 | I56: 838.83 | J56: 10% | K56: 520.07 | L56: 6 | M56: Compleated | N56: J. Patel
A57: HC-100055 | B57: 02.05.2024 | C57: North | D57: Wholesale | E57: KITCHEN | F57: Chef Knife | G57: Consumer | H57: 23 | I57: 59.83 | J57: 0.28 | K57: 21.54 | L57: 8 | M57: Completed | N57: L. Berger
A58: HC-100056 | B58: 05/24/2024 | C58: North | D58: e-commerce | E58: Lighting | F58: Brass Sconce | G58: Home Office | H58: 3 | I58: 143.44 | J58: 0.04 | K58: 65.98 | L58: 6 | M58: Completed | N58: J. Patel
A59: HC-100057 | B59: 17-Jan-24 | C59: East | D59: Online | E59: Furniture | F59: Oak Desk | G59: consumer | H59: One | I59: 795.51 | J59: 0.14 | K59: 493.21 | L59: 9 | M59: Completed | N59: R. Ibarra
A60: HC-100058 | B60: 2024/11/25 | C60: West | D60: Store | E60: Furniture | F60: Linen Sofa | G60: Consumer | H60: 3 | I60: 1285.91 | J60: 0.02 | K60: 848.70 | L60: 3 | M60: Completed | N60: S. Nguyen
A61: HC-100059 | B61: 05.07.2025 | C61: West | D61: retail | E61: Furniture | F61: Oak Desk | G61: Corporate | H61: 1 | I61: 789.19 | J61: 0.07 | K61: 489.30 | L61: 5 | M61: Completed | N61: P. Rossi
A62: HC-100060 | B62: 11/09/2024 | C62: South | D62: Store | E62: Textiles | F62: Linen Curtain | G62: Consumer | H62: 3 | I62: 90.34 | J62: 0.04 | K62: 40.65 | L62: 8 | M62: Completed | N62: M. Okonkwo
A63: HC-100061 | B63: 09-Nov-24 | C63: East | D63: Store | E63: Lighting | F63: Pendant Light | G63: Consumer | H63: 2 | I63: 153.34 | J63: 1% | K63: 76.67 | L63: 9 | M63: Completed | N63: R. Ibarra
A64: HC-100062 | B64: 2025/08/29 | C64: north | D64: Store | E64: Textiles | F64: Cotton Duvet | G64: Consumer | H64: 4 | I64: 124.67 | J64: 0.00 | K64: 54.86 | L64: 1 | M64: Returned | N64: S. Nguyen
A65: HC-100063 | B65: 24.09.2025 | C65: West | D65: Wholesale | E65: Furniture | F65: Lounge Chair | G65: Consumer | H65: 24 | I65: 470.36 | J65: 0.30 | K65: 282.22 | L65: 7 | M65: Completed | N65: M. Okonkwo
A66: HC-100064 | B66: 07/18/2024 | C66: West | D66: Store | E66: Textiles | F66: Cotton Duvet | G66: Consumer | H66: 2 | I66: 113.54 | J66: 0.08 | K66: 49.96 | L66: 5 | M66: Completed | N66: M. Okonkwo
A67: HC-100065 | B67: 02-Sep-25 | C67: North | D67: Online | E67: Kitchen | F67: Cast Skillet | G67: home office | H67: 2 | I67: 53.40 | J67: 0.09 | K67: 21.36 | L67: 4 | M67: Completed | N67: R. Ibarra
A68: HC-100066 | B68: 2024/05/23 | C68: West | D68: e-commerce | E68: Lighting | F68: Pendant Light | G68: Consumer | H68: 3 | I68: 193.50 | J68: 0.03 | K68: 96.75 | L68: 5 | M68: Completed | N68: R. Ibarra
... A82: HC-100080 | B82: 06/24/2024 | C82: East | D82: Online | E82: Furniture | F82: Walnut Shelf | G82: Consumer | H82: 2 | I82: 205.03 | J82: 0.17 | K82: 112.77 | L82: 13 | M82: Completed | N82: K. Mensah
A83: HC-100081 | B83: 25-Jul-25 | C83: West | D83: retail | E83: Textiles | F83: Wool Throw | H83: 2 | I83: 69.29 | J83: 10% | K83: 29.10 | L83: 3 | M83: Completed | N83: P. Rossi
A84: HC-100082 | B84: 2025/07/11 | C84: West | D84: Wholesale | E84: Furniture | F84: Walnut Shelf | G84: Home Office | H84: 22 | I84: 211.05 | J84: 0.28 | K84: 116.08 | L84: 6 | M84: Completed | N84: R. Ibarra
A85: HC-100083 | B85: 23.08.2024 | C85: East | D85: Store | E85: Kitchen | F85: Ceramic Set | G85: Consumer | H85: 4 | I85: 75.32 | J85: 0.11 | K85: 28.62 | L85: 6 | M85: Completed | N85: M. Okonkwo
A86: HC-100084 | B86: 03/05/2025 | C86: South | D86: Store | E86: Lighting | F86: Arc Lamp | G86: Corporate | H86: 1 | I86: 298.13 | J86: 0.10 | K86: 143.10 | L86: 8 | M86: complete | N86: P. Rossi
A87: HC-100085 | B87: 11-Jul-24 | C87: East | D87: e-commerce | E87: Textiles | F87: Cotton Duvet | G87: Consumer | H87: 3 | I87: 111.02 | J87: 0.13 | K87: 48.85 | L87: 6 | M87: Completed | N87: M. Okonkwo
A88: HC-100086 | B88: 2025/01/07 | C88: West | D88: Online | E88: Textiles | F88: Cotton Duvet | G88: Home Office | H88: 2 | I88: $111.78 | J88: 0.14 | K88: 49.18 | L88: 1 | M88: Completed | N88: L. Berger
A89: HC-100087 | B89: 16.01.2024 | C89: East | D89: Store | E89: Kitchen | F89: Cast Skillet | G89: Corporate | H89: 1 | I89: 47.25 | J89: 0.08 | K89: 18.90 | L89: 8 | M89: Completed | N89: M. Okonkwo
A90: HC-100088 | B90: 09/07/2025 | C90: West | D90: Online | E90: Textiles | F90: Linen Curtain | G90: Consumer | H90: 3 | I90: 90.50 | J90: 0.17 | K90: 40.72 | L90: 4 | M90: Completed | N90: J. Patel
A91: HC-100089 | B91: 14-Oct-24 | C91: WEST | D91: Store | E91: Furniture | F91: Walnut Shelf | G91: corporate | H91: 1 | I91: 232.34 | J91: 2% | K91: 127.79 | L91: 1 | M91: complete | N91: J. Patel
A92: HC-100090 | B92: 2025/01/21 | C92: South | D92: Store | E92: Furniture | F92: Linen Sofa | G92: Consumer | H92: 4 | I92: 1152.20 | J92: 0.11 | K92: 760.45 | L92: 7 | M92: Completed | N92: P. Rossi
A93: HC-100091 | B93: 04.02.2024 | C93: West | D93: Store | E93: Lighting | F93: Pendant Light | G93: Consumer | H93: 3 | I93: 187.97 | J93: 0.07 | K93: 93.98 | L93: 7 | M93: Completed | N93: P. Rossi
A94: HC-100092 | B94: 06/19/2024 | C94: North | D94: Wholesale | E94: Kitchen | F94: Cast Skillet | G94: Consumer | H94: 22 | I94: 58.06 | J94: 0.27 | K94: 23.23 | L94: 4 | M94: Completed | N94: A. Shah
A95: HC-100093 | B95: 26-Jun-25 | C95: South | D95: e-commerce | E95: Furniture | F95: Lounge Chair | G95: Consumer | H95: 3 | I95: 469.94 | J95: 0.14 | K95: 281.96 | L95: 2 | M95: Completed | N95: S. Nguyen
... A136: HC-100134 | B136: 2024/07/26 | C136: South | D136: Store | E136: Textiles | F136: Cotton Duvet | G136: Consumer | H136: 2 | I136: 115.11 | J136: 0.05 | K136: 50.65 | L136: 7 | M136: Completed | N136: S. Nguyen
A137: HC-100135 | B137: 02.04.2025 | C137: Sout | D137: Store | E137: Textiles | F137: Wool Throw | H137: 2 | I137: 73.98 | J137: 0.01 | K137: 31.07 | L137: 7 | M137: Completed | N137: L. Berger
A138: HC-100136 | B138: 12/17/2024 | C138: North | D138: Store | E138: Textiles | F138: Wool Throw | G138: Consumer | H138: 3 | I138: 71.66 | J138: 0.07 | K138: 30.10 | L138: 7 | M138: Completed | N138: L. Berger
A139: HC-100137 | B139: 05-Sep-24 | C139: WEST | D139: Store | E139: Kitchen | F139: Chef Knife | G139: Consumer | H139: 2 | I139: 68.79 | J139: 8% | K139: 24.76 | L139: 7 | M139: Completed | N139: S. Nguyen
A140: HC-100138 | B140: 2024/01/28 | C140: East | D140: Store | E140: Textiles | F140: Wool Throw | G140: Consumer | H140: 2 | I140: 66.04 | J140: 7% | K140: 27.74 | L140: 6 | M140: Completed | N140: P. Rossi
A141: HC-100139 | B141: 30.06.2025 | C141: South | D141: Store | E141: Furniture | F141: Oak Desk | G141: consumer | H141: 3 | I141: 890.44 | J141: 0.11 | K141: 552.07 | L141: 7 | M141: Completed | N141: K. Mensah
A142: HC-100140 | B142: 12/04/2024 | C142: East | D142: Store | E142: Furniture | F142: Linen Sofa | G142: Home Office | H142: 2 | I142: 1119.44 | J142: 0.02 | K142: 738.83 | L142: 9 | M142: Completed | N142: S. Nguyen
A143: HC-100141 | B143: 24-Mar-24 | C143: North | D143: Online | E143: FURNITURE | F143: Oak Desk | G143: Consumer | H143: 1 | I143: 883.26 | J143: 0.15 | K143: 547.62 | L143: 7 | M143: Completed | N143: S. Nguyen
A144: HC-100142 | B144: 2025/05/21 | C144: North | D144: retail | E144: Textiles | F144: Cotton Duvet | G144: Corporate | H144: 2 | I144: 125.03 | J144: 0.11 | K144: 55.01 | L144: 6 | M144: Completed | N144: L. Berger
A145: HC-100143 | B145: 11.07.2025 | C145: East | D145: Store | E145: Textiles | F145: Cotton Duvet | G145: Consumer | H145: 1 | I145: 103.34 | J145: 0.03 | K145: 45.47 | L145: 7 | M145: Cancelled | N145: J. Patel
A146: HC-100144 | B146: 08/25/2025 | C146: West | D146: Store | E146: Textiles | F146: Wool Throw | G146: Consumer | H146: 1 | I146: 74.95 | J146: 0.07 | K146: 31.48 | L146: 6 | M146: Completed | N146: K. Mensah
A147: HC-100145 | B147: 19-Jan-24 | C147: West | D147: Online | E147: Textiles | F147: Wool Throw | G147: Consumer | H147: 3 | I147: 73.05 | J147: 0.17 | K147: 30.68 | L147: 8 | M147: Completed | N147: M. Okonkwo
A148: HC-100146 | B148: 2025/08/06 | C148: West | D148: Online | E148: Furniture | F148: Lounge Chair | G148: Consumer | H148: 1 | I148: 461.39 | J148: 0.08 | K148: 276.83 | L148: 7 | M148: Completed | N148: A. Shah
A149: HC-100147 | B149: 19.03.2025 | C149: South | D149: e-commerce | E149: FURNITURE | F149: Walnut Shelf | G149: Consumer | H149: 3 | I149: 212.00 | J149: 0.06 | K149: 116.60 | L149: 7 | M149: Completed | N149: P. Rossi
... A154: HC-100152 | B154: 08/03/2024 | C154: North | D154: web | E154: Textiles | F154: Wool Throw | G154: Corporate | H154: 3 | I154: 78.69 | J154: 0.04 | K154: 33.05 | L154: 6 | M154: Completed | N154: L. Berger
A155: HC-100153 | B155: 30-Jul-25 | C155: West | D155: Store | E155: FURNITURE | F155: Walnut Shelf | H155: 4 | I155: 230.63 | J155: 0.04 | K155: 126.84 | L155: 7 | M155: Completed | N155: S. Nguyen
A156: HC-100154 | B156: 2024/03/05 | C156: North | D156: Online | E156: Furniture | F156: Walnut Shelf | G156: Home Office | H156: 1 | I156: 229.27 | J156: 0.05 | K156: 126.10 | L156: 5 | M156: Returned | N156: M. Okonkwo
A157: HC-100155 | B157: 01.02.2024 | C157: North | D157: Store | E157: Textiles | F157: Wool Throw | G157: Corporate | H157: 1 | I157: 70.08 | J157: 5% | K157: 29.43 | L157: 6 | M157: Completed | N157: P. Rossi
A158: HC-100156 | B158: 07/27/2024 | C158: West | D158: Store | E158: Furniture | F158: Lounge Chair | G158: Consumer | H158: 1 | I158: $447.10 | J158: 0.07 | K158: 268.26 | L158: 5 | M158: Returned | N158: A. Shah
A159: HC-100157 | B159: 23-Dec-24 | C159: West | D159: Store | E159: Kitchen | F159: Cast Skillet | G159: Consumer | H159: 4 | I159: 57.84 | J159: 0.03 | K159: 23.13 | L159: 6 | M159: Completed | N159: R. Ibarra
A160: HC-100158 | B160: 2025/03/12 | C160: West | D160: Online | E160: Textiles | F160: Wool Throw | G160: Consumer | H160: 2 | I160: 70.39 | J160: 0.03 | K160: 29.57 | L160: 7 | M160: Completed | N160: L. Berger
A161: HC-100159 | B161: 12.03.2025 | C161: East | D161: Store | E161: Lighting | F161: Arc Lamp | G161: Consumer | H161: 4 | I161: 294.85 | J161: 0.00 | K161: 141.53 | L161: 8 | M161: Completed | N161: S. Nguyen
A162: HC-100160 | B162: 08/01/2025 | C162: South | D162: Store | E162: Furniture | F162: Linen Sofa | G162: Consumer | H162: 3 | I162: 1155.67 | J162: 0.12 | K162: 762.74 | L162: 8 | M162: Completed | N162: P. Rossi
A163: HC-100161 | B163: 22-Nov-24 | C163: East | D163: Store | E163: Lighting | F163: Arc Lamp | G163: Consumer | H163: 4 | I163: 267.04 | J163: 0.04 | K163: 128.18 | L163: 8 | M163: Completed | N163: A. Shah
A164: HC-100162 | B164: 2025/06/22 | C164: Eas | D164: Wholesale | E164: Furniture | F164: Walnut Shelf | G164: Consumer | H164: 28 | I164: 192.58 | J164: 0.23 | K164: 105.92 | L164: 8 | M164: Completed | N164: A. Shah
A165: HC-100163 | B165: 26.03.2025 | C165: North | D165: retail | E165: Kitchen | F165: Chef Knife | G165: Consumer | H165: 3 | I165: 68.12 | J165: 0.11 | K165: 24.52 | L165: 6 | M165: Completed | N165: K. Mensah
A166: HC-100164 | B166: 12/09/2024 | C166: South | D166: Online | E166: Lighting | F166: Brass Sconce | G166: Corporate | H166: 4 | I166: 149.68 | J166: 0.17 | K166: 68.85 | L166: N/A | M166: Completed | N166: A. Shah
A167: HC-100165 | B167: 26-Jan-25 | C167: North | D167: Online | E167: Textiles | F167: Linen Curtain | G167: Consumer | H167: 3 | I167: 100.38 | J167: 0.08 | K167: 45.17 | L167: 8 | M167: Completed | N167: S. Nguyen
... A201: HC-100199 | B201: 07.05.2024 | C201: North | D201: Store | E201: Furniture | F201: Lounge Chair | G201: Consumer | H201: 1 | I201: 487.93 | J201: 0.10 | K201: 292.76 | L201: 6 | M201: Completed | N201: P. Rossi
A202: HC-100200 | B202: 06/05/2025 | C202: SOUTH | D202: Online | E202: Furniture | F202: Linen Sofa | H202: 2 | I202: 1189.15 | J202: 0.02 | K202: 784.84 | L202: 4 | M202: Compleated | N202: K. Mensah
A203: HC-100201 | B203: 16-Jul-24 | C203: East | D203: e-commerce | E203: Lighting | F203: Brass Sconce | G203: Corporate | H203: 2 | I203: $131.18 | J203: 0.15 | K203: 60.34 | L203: 7 | M203: Cancelled | N203: K. Mensah
A204: HC-100202 | B204: 2025/07/02 | C204: North | D204: Wholesale | E204: Furniture | F204: Walnut Shelf | G204: Consumer | H204: 35 | I204: 205.37 | J204: 0.24 | K204: 112.95 | L204: 3 | M204: Completed | N204: S. Nguyen
A205: HC-100203 | B205: 26.01.2024 | C205: North | D205: Online | E205: Lighting | F205: Brass Sconce | G205: Corporate | H205: 3 | I205: 140.46 | J205: 0.12 | K205: 64.61 | L205: 5 | M205: Completed | N205: L. Berger
A206: HC-100204 | B206: 12/01/2024 | C206: North | D206: e-commerce | E206: Kitchen | F206: Ceramic Set | G206: Corporate | H206: 4 | I206: 92.05 | J206: 0.04 | K206: 34.98 | L206: 8 | M206: Completed | N206: P. Rossi
A207: HC-100205 | B207: 16-Jul-25 | C207: South | D207: Online | E207: Furniture | F207: Lounge Chair | G207: Home Office | H207: 1 | I207: 445.59 | J207: 0.12 | K207: 267.35 | L207: 2 | M207: Completed | N207: S. Nguyen
...

Sheet Lookup_Maps
A1: Alias maps
A2: The cleaning stage applies these maps. They are reproduced here so the workbook can be audited without opening the Python code.
B4: Alias | C4: Standard value
B5: north | C5: North
B6: nort | C6: North
B7: south | C7: South
B8: sout | C8: South
B9: east | C9: East
B10: eas | C10: East
B11: west | C11: West
B12: wes | C12: West
B14: Alias | C14: Standard value
B15: store | C15: Store
B16: retail | C16: Store
... B49: home-office | C49: Home Office

Sheet Cleaned_Data
A1: OrderID | B1: OrderDate | C1: Region | D1: Channel | E1: Category | F1: Product | G1: Segment | H1: Quantity | I1: UnitPrice | J1: Discount | K1: UnitCost | L1: ShipDays | M1: Status | N1: SalesRep | O1: QtyAdjusted | P1: GrossRevenue | Q1: NetRevenue | R1: TotalCost | S1: Margin | T1: Year | U1: Quarter | V1: YearMonth | W1: LateFlag | X1: HighValueFlag | Y1: ReturnFlag
A2: HC-100000 | B2: 45798 | C2: West | D2: Online | E2: Furniture | F2: Linen Sofa | G2: Consumer | H2: 2 | I2: 1307.21 | J2: 0.14 | K2: 862.76 | L2: 4 | M2: Completed | N2: J. Patel | O2: No | P2: =H2*I2 | Q2: =P2*(1-J2) | R2: =H2*K2 | S2: =IF(Q2=0,"",(Q2-R2)/Q2) | T2: =YEAR(B2) | U2: =YEAR(B2)&"-Q"&ROUNDUP(MONTH(B2)/3,0) | V2: =TEXT(B2,"YYYY-MM") | W2: =IF(L2="","",IF(L2>pLateDays,1,0)) | X2: =IF(Q2>=pHighCutoff,1,0) | Y2: =IF(M2="Returned",1,0)
A3: HC-100001 | B3: 45538 | C3: West | D3: Online | E3: Furniture | F3: Lounge Chair | G3: Home Office | H3: 2 | I3: 453.45 | J3: 0.03 | K3: 272.07 | L3: 10 | M3: Completed | N3: R. Ibarra | O3: No | P3: =H3*I3 | Q3: =P3*(1-J3) | R3: =H3*K3 | S3: =IF(Q3=0,"",(Q3-R3)/Q3) | T3: =YEAR(B3) | U3: =YEAR(B3)&"-Q"&ROUNDUP(MONTH(B3)/3,0) | V3: =TEXT(B3,"YYYY-MM") | W3: =IF(L3="","",IF(L3>pLateDays,1,0)) | X3: =IF(Q3>=pHighCutoff,1,0) | Y3: =IF(M3="Returned",1,0)
A4: HC-100002 | B4: 45720 | C4: West | D4: Online | E4: Lighting | F4: Arc Lamp | G4: Corporate | H4: 3 | I4: 292.13 | J4: 0.13 | K4: 140.22 | L4: 6 | M4: Completed | N4: L. Berger | O4: No | P4: =H4*I4 | Q4: =P4*(1-J4) | R4: =H4*K4 | S4: =IF(Q4=0,"",(Q4-R4)/Q4) | T4: =YEAR(B4) | U4: =YEAR(B4)&"-Q"&ROUNDUP(MONTH(B4)/3,0) | V4: =TEXT(B4,"YYYY-MM") | W4: =IF(L4="","",IF(L4>pLateDays,1,0)) | X4: =IF(Q4>=pHighCutoff,1,0) | Y4: =IF(M4="Returned",1,0)
A5: HC-100003 | B5: 45795 | C5: East | D5: Online | E5: Furniture | F5: Walnut Shelf | G5: Consumer | H5: 2 | I5: 188.96 | J5: 0.09 | K5: 103.93 | L5: 6 | M5: Completed | N5: A. Shah | O5: No | P5: =H5*I5 | Q5: =P5*(1-J5) | R5: =H5*K5 | S5: =IF(Q5=0,"",(Q5-R5)/Q5) | T5: =YEAR(B5) | U5: =YEAR(B5)&"-Q"&ROUNDUP(MONTH(B5)/3,0) | V5: =TEXT(B5,"YYYY-MM") | W5: =IF(L5="","",IF(L5>pLateDays,1,0)) | X5: =IF(Q5>=pHighCutoff,1,0) | Y5: =IF(M5="Returned",1,0)
A6: HC-100004 | B6: 45360 | C6: West | D6: Online | E6: Furniture | F6: Lounge Chair | G6: Consumer | H6: 2 | I6: 495.08 | J6: 0.04 | K6: 297.05 | L6: 5 | M6: Completed | N6: P. Rossi | O6: No | P6: =H6*I6 | Q6: =P6*(1-J6) | R6: =H6*K6 | S6: =IF(Q6=0,"",(Q6-R6)/Q6) | T6: =YEAR(B6) | U6: =YEAR(B6)&"-Q"&ROUNDUP(MONTH(B6)/3,0) | V6: =TEXT(B6,"YYYY-MM") | W6: =IF(L6="","",IF(L6>pLateDays,1,0)) | X6: =IF(Q6>=pHighCutoff,1,0) | Y6: =IF(M6="Returned",1,0)
A7: HC-100005 | B7: 45503 | C7: North | D7: Wholesale | E7: Lighting | F7: Brass Sconce | G7: Corporate | H7: 13 | I7: 141.77 | J7: 0.18 | K7: 65.22 | L7: 3 | M7: Completed | N7: R. Ibarra | O7: No | P7: =H7*I7 | Q7: =P7*(1-J7) | R7: =H7*K7 | S7: =IF(Q7=0,"",(Q7-R7)/Q7) | T7: =YEAR(B7) | U7: =YEAR(B7)&"-Q"&ROUNDUP(MONTH(B7)/3,0) | V7: =TEXT(B7,"YYYY-MM") | W7: =IF(L7="","",IF(L7>pLateDays,1,0)) | X7: =IF(Q7>=pHighCutoff,1,0) | Y7: =IF(M7="Returned",1,0)
A8: HC-100006 | B8: 45404 | C8: North | D8: Online | E8: Furniture | F8: Linen Sofa | G8: Home Office | H8: 3 | I8: 1219.37 | J8: 0.11 | K8: 804.79 | L8: 5 | M8: Completed | N8: R. Ibarra | O8: No | P8: =H8*I8 | Q8: =P8*(1-J8) | R8: =H8*K8 | S8: =IF(Q8=0,"",(Q8-R8)/Q8) | T8: =YEAR(B8) | U8: =YEAR(B8)&"-Q"&ROUNDUP(MONTH(B8)/3,0) | V8: =TEXT(B8,"YYYY-MM") | W8: =IF(L8="","",IF(L8>pLateDays,1,0)) | X8: =IF(Q8>=pHighCutoff,1,0) | Y8: =IF(M8="Returned",1,0)
A9: HC-100007 | B9: 45574 | C9: West | D9: Wholesale | E9: Furniture | F9: Oak Desk | G9: Unknown | H9: 16 | I9: 863.15 | J9: 0.14 | K9: 535.15 | L9: 6 | M9: Completed | N9: S. Nguyen | O9: No | P9: =H9*I9 | Q9: =P9*(1-J9) | R9: =H9*K9 | S9: =IF(Q9=0,"",(Q9-R9)/Q9) | T9: =YEAR(B9) | U9: =YEAR(B9)&"-Q"&ROUNDUP(MONTH(B9)/3,0) | V9: =TEXT(B9,"YYYY-MM") | W9: =IF(L9="","",IF(L9>pLateDays,1,0)) | X9: =IF(Q9>=pHighCutoff,1,0) | Y9: =IF(M9="Returned",1,0)
A10: HC-100008 | B10: 45533 | C10: West | D10: Store | E10: Lighting | F10: Brass Sconce | G10: Home Office | H10: 2 | I10: 132.49 | J10: 0.11 | K10: 60.94 | L10: 3 | M10: Completed | N10: M. Okonkwo | O10: No | P10: =H10*I10 | Q10: =P10*(1-J10) | R10: =H10*K10 | S10: =IF(Q10=0,"",(Q10-R10)/Q10) | T10: =YEAR(B10) | U10: =YEAR(B10)&"-Q"&ROUNDUP(MONTH(B10)/3,0) | V10: =TEXT(B10,"YYYY-MM") | W10: =IF(L10="","",IF(L10>pLateDays,1,0)) | X10: =IF(Q10>=pHighCutoff,1,0) | Y10: =IF(M10="Returned",1,0)
A11: HC-100009 | B11: 45501 | C11: West | D11: Store | E11: Furniture | F11: Oak Desk | G11: Unknown | H11: 4 | I11: 796.89 | J11: 0.02 | K11: 494.07 | L11: 3 | M11: Completed | N11: J. Patel | O11: No | P11: =H11*I11 | Q11: =P11*(1-J11) | R11: =H11*K11 | S11: =IF(Q11=0,"",(Q11-R11)/Q11) | T11: =YEAR(B11) | U11: =YEAR(B11)&"-Q"&ROUNDUP(MONTH(B11)/3,0) | V11: =TEXT(B11,"YYYY-MM") | W11: =IF(L11="","",IF(L11>pLateDays,1,0)) | X11: =IF(Q11>=pHighCutoff,1,0) | Y11: =IF(M11="Returned",1,0)
A12: HC-100010 | B12: 45740 | C12: North | D12: Online | E12: Textiles | F12: Cotton Duvet | G12: Consumer | H12: 1 | I12: 112.78 | J12: 0.04 | K12: 49.62 | L12: 5 | M12: Returned | N12: P. Rossi | O12: No | P12: =H12*I12 | Q12: =P12*(1-J12) | R12: =H12*K12 | S12: =IF(Q12=0,"",(Q12-R12)/Q12) | T12: =YEAR(B12) | U12: =YEAR(B12)&"-Q"&ROUNDUP(MONTH(B12)/3,0) | V12: =TEXT(B12,"YYYY-MM") | W12: =IF(L12="","",IF(L12>pLateDays,1,0)) | X12: =IF(Q12>=pHighCutoff,1,0) | Y12: =IF(M12="Returned",1,0)
A13: HC-100011 | B13: 45905 | C13: West | D13: Online | E13: Lighting | F13: Pendant Light | G13: Consumer | H13: 2 | I13: 168.74 | J13: 0.02 | K13: 84.37 | L13: 4 | M13: Completed | N13: K. Mensah | O13: No | P13: =H13*I13 | Q13: =P13*(1-J13) | R13: =H13*K13 | S13: =IF(Q13=0,"",(Q13-R13)/Q13) | T13: =YEAR(B13) | U13: =YEAR(B13)&"-Q"&ROUNDUP(MONTH(B13)/3,0) | V13: =TEXT(B13,"YYYY-MM") | W13: =IF(L13="","",IF(L13>pLateDays,1,0)) | X13: =IF(Q13>=pHighCutoff,1,0) | Y13: =IF(M13="Returned",1,0)
... A133: HC-100131 | B133: 45776 | C133: South | D133: Online | E133: Lighting | F133: Arc Lamp | G133: Consumer | H133: 1 | I133: 291 | J133: 0.04 | K133: 139.68 | L133: 6 | M133: Completed | N133: L. Berger | O133: No | P133: =H133*I133 | Q133: =P133*(1-J133) | R133: =H133*K133 | S133: =IF(Q133=0,"",(Q133-R133)/Q133) | T133: =YEAR(B133) | U133: =YEAR(B133)&"-Q"&ROUNDUP(MONTH(B133)/3,0) | V133: =TEXT(B133,"YYYY-MM") | W133: =IF(L133="","",IF(L133>pLateDays,1,0)) | X133: =IF(Q133>=pHighCutoff,1,0) | Y133: =IF(M133="Returned",1,0)
A134: HC-100132 | B134: 45633 | C134: East | D134: Store | E134: Textiles | F134: Linen Curtain | G134: Consumer | H134: 5 | I134: 85.4 | J134: 0.12 | K134: 38.43 | M134: Completed | N134: L. Berger | O134: No | P134: =H134*I134 | Q134: =P134*(1-J134) | R134: =H134*K134 | S134: =IF(Q134=0,"",(Q134-R134)/Q134) | T134: =YEAR(B134) | U134: =YEAR(B134)&"-Q"&ROUNDUP(MONTH(B134)/3,0) | V134: =TEXT(B134,"YYYY-MM") | W134: =IF(L134="","",IF(L134>pLateDays,1,0)) | X134: =IF(Q134>=pHighCutoff,1,0) | Y134: =IF(M134="Returned",1,0)
A135: HC-100133 | B135: 45497 | C135: South | D135: Wholesale | E135: Furniture | F135: Walnut Shelf | G135: Consumer | H135: 26 | I135: 236.05 | J135: 0.13 | K135: 129.83 | L135: 4 | M135: Cancelled | N135: P. Rossi | O135: No | P135: =H135*I135 | Q135: =P135*(1-J135) | R135: =H135*K135 | S135: =IF(Q135=0,"",(Q135-R135)/Q135) | T135: =YEAR(B135) | U135: =YEAR(B135)&"-Q"&ROUNDUP(MONTH(B135)/3,0) | V135: =TEXT(B135,"YYYY-MM") | W135: =IF(L135="","",IF(L135>pLateDays,1,0)) | X135: =IF(Q135>=pHighCutoff,1,0) | Y135: =IF(M135="Returned",1,0)
A136: HC-100134 | B136: 45499 | C136: South | D136: Store | E136: Textiles | F136: Cotton Duvet | G136: Consumer | H136: 2 | I136: 115.11 | J136: 0.05 | K136: 50.65 | L136: 7 | M136: Completed | N136: S. Nguyen | O136: No | P136: =H136*I136 | Q136: =P136*(1-J136) | R136: =H136*K136 | S136: =IF(Q136=0,"",(Q136-R136)/Q136) | T136: =YEAR(B136) | U136: =YEAR(B136)&"-Q"&ROUNDUP(MONTH(B136)/3,0) | V136: =TEXT(B136,"YYYY-MM") | W136: =IF(L136="","",IF(L136>pLateDays,1,0)) | X136: =IF(Q136>=pHighCutoff,1,0) | Y136: =IF(M136="Returned",1,0)
A137: HC-100135 | B137: 45749 | C137: South | D137: Store | E137: Textiles | F137: Wool Throw | G137: Unknown | H137: 2 | I137: 73.98 | J137: 0.01 | K137: 31.07 | L137: 7 | M137: Completed | N137: L. Berger | O137: No | P137: =H137*I137 | Q137: =P137*(1-J137) | R137: =H137*K137 | S137: =IF(Q137=0,"",(Q137-R137)/Q137) | T137: =YEAR(B137) | U137: =YEAR(B137)&"-Q"&ROUNDUP(MONTH(B137)/3,0) | V137: =TEXT(B137,"YYYY-MM") | W137: =IF(L137="","",IF(L137>pLateDays,1,0)) | X137: =IF(Q137>=pHighCutoff,1,0) | Y137: =IF(M137="Returned",1,0)
A138: HC-100136 | B138: 45643 | C138: North | D138: Store | E138: Textiles | F138: Wool Throw | G138: Consumer | H138: 3 | I138: 71.66 | J138: 0.07 | K138: 30.1 | L138: 7 | M138: Completed | N138: L. Berger | O138: No | P138: =H138*I138 | Q138: =P138*(1-J138) | R138: =H138*K138 | S138: =IF(Q138=0,"",(Q138-R138)/Q138) | T138: =YEAR(B138) | U138: =YEAR(B138)&"-Q"&ROUNDUP(MONTH(B138)/3,0) | V138: =TEXT(B138,"YYYY-MM") | W138: =IF(L138="","",IF(L138>pLateDays,1,0)) | X138: =IF(Q138>=pHighCutoff,1,0) | Y138: =IF(M138="Returned",1,0)
A139: HC-100137 | B139: 45540 | C139: West | D139: Store | E139: Kitchen | F139: Chef Knife | G139: Consumer | H139: 2 | I139: 68.79 | J139: 0.08 | K139: 24.76 | L139: 7 | M139: Completed | N139: S. Nguyen | O139: No | P139: =H139*I139 | Q139: =P139*(1-J139) | R139: =H139*K139 | S139: =IF(Q139=0,"",(Q139-R139)/Q139) | T139: =YEAR(B139) | U139: =YEAR(B139)&"-Q"&ROUNDUP(MONTH(B139)/3,0) | V139: =TEXT(B139,"YYYY-MM") | W139: =IF(L139="","",IF(L139>pLateDays,1,0)) | X139: =IF(Q139>=pHighCutoff,1,0) | Y139: =IF(M139="Returned",1,0)
A140: HC-100138 | B140: 45319 | C140: East | D140: Store | E140: Textiles | F140: Wool Throw | G140: Consumer | H140: 2 | I140: 66.04 | J140: 0.07 | K140: 27.74 | L140: 6 | M140: Completed | N140: P. Rossi | O140: No | P140: =H140*I140 | Q140: =P140*(1-J140) | R140: =H140*K140 | S140: =IF(Q140=0,"",(Q140-R140)/Q140) | T140: =YEAR(B140) | U140: =YEAR(B140)&"-Q"&ROUNDUP(MONTH(B140)/3,0) | V140: =TEXT(B140,"YYYY-MM") | W140: =IF(L140="","",IF(L140>pLateDays,1,0)) | X140: =IF(Q140>=pHighCutoff,1,0) | Y140: =IF(M140="Returned",1,0)
A141: HC-100139 | B141: 45838 | C141: South | D141: Store | E141: Furniture | F141: Oak Desk | G141: Consumer | H141: 3 | I141: 890.44 | J141: 0.11 | K141: 552.07 | L141: 7 | M141: Completed | N141: K. Mensah | O141: No | P141: =H141*I141 | Q141: =P141*(1-J141) | R141: =H141*K141 | S141: =IF(Q141=0,"",(Q141-R141)/Q141) | T141: =YEAR(B141) | U141: =YEAR(B141)&"-Q"&ROUNDUP(MONTH(B141)/3,0) | V141: =TEXT(B141,"YYYY-MM") | W141: =IF(L141="","",IF(L141>pLateDays,1,0)) | X141: =IF(Q141>=pHighCutoff,1,0) | Y141: =IF(M141="Returned",1,0)
A142: HC-100140 | B142: 45630 | C142: East | D142: Store | E142: Furniture | F142: Linen Sofa | G142: Home Office | H142: 2 | I142: 1119.44 | J142: 0.02 | K142: 738.83 | L142: 9 | M142: Completed | N142: S. Nguyen | O142: No | P142: =H142*I142 | Q142: =P142*(1-J142) | R142: =H142*K142 | S142: =IF(Q142=0,"",(Q142-R142)/Q142) | T142: =YEAR(B142) | U142: =YEAR(B142)&"-Q"&ROUNDUP(MONTH(B142)/3,0) | V142: =TEXT(B142,"YYYY-MM") | W142: =IF(L142="","",IF(L142>pLateDays,1,0)) | X142: =IF(Q142>=pHighCutoff,1,0) | Y142: =IF(M142="Returned",1,0)
A143: HC-100141 | B143: 45375 | C143: North | D143: Online | E143: Furniture | F143: Oak Desk | G143: Consumer | H143: 1 | I143: 883.26 | J143: 0.15 | K143: 547.62 | L143: 7 | M143: Completed | N143: S. Nguyen | O143: No | P143: =H143*I143 | Q143: =P143*(1-J143) | R143: =H143*K143 | S143: =IF(Q143=0,"",(Q143-R143)/Q143) | T143: =YEAR(B143) | U143: =YEAR(B143)&"-Q"&ROUNDUP(MONTH(B143)/3,0) | V143: =TEXT(B143,"YYYY-MM") | W143: =IF(L143="","",IF(L143>pLateDays,1,0)) | X143: =IF(Q143>=pHighCutoff,1,0) | Y143: =IF(M143="Returned",1,0)
A144: HC-100142 | B144: 45798 | C144: North | D144: Store | E144: Textiles | F144: Cotton Duvet | G144: Corporate | H144: 2 | I144: 125.03 | J144: 0.11 | K144: 55.01 | L144: 6 | M144: Completed | N144: L. Berger | O144: No | P144: =H144*I144 | Q144: =P144*(1-J144) | R144: =H144*K144 | S144: =IF(Q144=0,"",(Q144-R144)/Q144) | T144: =YEAR(B144) | U144: =YEAR(B144)&"-Q"&ROUNDUP(MONTH(B144)/3,0) | V144: =TEXT(B144,"YYYY-MM") | W144: =IF(L144="","",IF(L144>pLateDays,1,0)) | X144: =IF(Q144>=pHighCutoff,1,0) | Y144: =IF(M144="Returned",1,0)
A145: HC-100143 | B145: 45849 | C145: East | D145: Store | E145: Textiles | F145: Cotton Duvet | G145: Consumer | H145: 1 | I145: 103.34 | J145: 0.03 | K145: 45.47 | L145: 7 | M145: Cancelled | N145: J. Patel | O145: No | P145: =H145*I145 | Q145: =P145*(1-J145) | R145: =H145*K145 | S145: =IF(Q145=0,"",(Q145-R145)/Q145) | T145: =YEAR(B145) | U145: =YEAR(B145)&"-Q"&ROUNDUP(MONTH(B145)/3,0) | V145: =TEXT(B145,"YYYY-MM") | W145: =IF(L145="","",IF(L145>pLateDays,1,0)) | X145: =IF(Q145>=pHighCutoff,1,0) | Y145: =IF(M145="Returned",1,0)
A146: HC-100144 | B146: 45894 | C146: West | D146: Store | E146: Textiles | F146: Wool Throw | G146: Consumer | H146: 1 | I146: 74.95 | J146: 0.07 | K146: 31.48 | L146: 6 | M146: Completed | N146: K. Mensah | O146: No | P146: =H146*I146 | Q146: =P146*(1-J146) | R146: =H146*K146 | S146: =IF(Q146=0,"",(Q146-R146)/Q146) | T146: =YEAR(B146) | U146: =YEAR(B146)&"-Q"&ROUNDUP(MONTH(B146)/3,0) | V146: =TEXT(B146,"YYYY-MM") | W146: =IF(L146="","",IF(L146>pLateDays,1,0)) | X146: =IF(Q146>=pHighCutoff,1,0) | Y146: =IF(M146="Returned",1,0)
... A152: HC-100150 | B152: 45554 | C152: North | D152: Online | E152: Kitchen | F152: Cast Skillet | G152: Corporate | H152: 1 | I152: 51.18 | J152: 0.1 | K152: 20.47 | L152: 8 | M152: Completed | N152: M. Okonkwo | O152: No | P152: =H152*I152 | Q152: =P152*(1-J152) | R152: =H152*K152 | S152: =IF(Q152=0,"",(Q152-R152)/Q152) | T152: =YEAR(B152) | U152: =YEAR(B152)&"-Q"&ROUNDUP(MONTH(B152)/3,0) | V152: =TEXT(B152,"YYYY-MM") | W152: =IF(L152="","",IF(L152>pLateDays,1,0)) | X152: =IF(Q152>=pHighCutoff,1,0) | Y152: =IF(M152="Returned",1,0)
A153: HC-100151 | B153: 45870 | C153: West | D153: Wholesale | E153: Kitchen | F153: Cast Skillet | G153: Consumer | H153: 26 | I153: 53.28 | J153: 0.31 | K153: 21.31 | M153: Completed | N153: J. Patel | O153: No | P153: =H153*I153 | Q153: =P153*(1-J153) | R153: =H153*K153 | S153: =IF(Q153=0,"",(Q153-R153)/Q153) | T153: =YEAR(B153) | U153: =YEAR(B153)&"-Q"&ROUNDUP(MONTH(B153)/3,0) | V153: =TEXT(B153,"YYYY-MM") | W153: =IF(L153="","",IF(L153>pLateDays,1,0)) | X153: =IF(Q153>=pHighCutoff,1,0) | Y153: =IF(M153="Returned",1,0)
A154: HC-100152 | B154: 45507 | C154: North | D154: Online | E154: Textiles | F154: Wool Throw | G154: Corporate | H154: 3 | I154: 78.69 | J154: 0.04 | K154: 33.05 | L154: 6 | M154: Completed | N154: L. Berger | O154: No | P154: =H154*I154 | Q154: =P154*(1-J154) | R154: =H154*K154 | S154: =IF(Q154=0,"",(Q154-R154)/Q154) | T154: =YEAR(B154) | U154: =YEAR(B154)&"-Q"&ROUNDUP(MONTH(B154)/3,0) | V154: =TEXT(B154,"YYYY-MM") | W154: =IF(L154="","",IF(L154>pLateDays,1,0)) | X154: =IF(Q154>=pHighCutoff,1,0) | Y154: =IF(M154="Returned",1,0)
A155: HC-100153 | B155: 45868 | C155: West | D155: Store | E155: Furniture | F155: Walnut Shelf | G155: Unknown | H155: 4 | I155: 230.63 | J155: 0.04 | K155: 126.84 | L155: 7 | M155: Completed | N155: S. Nguyen | O155: No | P155: =H155*I155 | Q155: =P155*(1-J155) | R155: =H155*K155 | S155: =IF(Q155=0,"",(Q155-R155)/Q155) | T155: =YEAR(B155) | U155: =YEAR(B155)&"-Q"&ROUNDUP(MONTH(B155)/3,0) | V155: =TEXT(B155,"YYYY-MM") | W155: =IF(L155="","",IF(L155>pLateDays,1,0)) | X155: =IF(Q155>=pHighCutoff,1,0) | Y155: =IF(M155="Returned",1,0)
A156: HC-100154 | B156: 45356 | C156: North | D156: Online | E156: Furniture | F156: Walnut Shelf | G156: Home Office | H156: 1 | I156: 229.27 | J156: 0.05 | K156: 126.1 | L156: 5 | M156: Returned | N156: M. Okonkwo | O156: No | P156: =H156*I156 | Q156: =P156*(1-J156) | R156: =H156*K156 | S156: =IF(Q156=0,"",(Q156-R156)/Q156) | T156: =YEAR(B156) | U156: =YEAR(B156)&"-Q"&ROUNDUP(MONTH(B156)/3,0) | V156: =TEXT(B156,"YYYY-MM") | W156: =IF(L156="","",IF(L156>pLateDays,1,0)) | X156: =IF(Q156>=pHighCutoff,1,0) | Y156: =IF(M156="Returned",1,0)
A157: HC-100155 | B157: 45323 | C157: North | D157: Store | E157: Textiles | F157: Wool Throw | G157: Corporate | H157: 1 | I157: 70.08 | J157: 0.05 | K157: 29.43 | L157: 6 | M157: Completed | N157: P. Rossi | O157: No | P157: =H157*I157 | Q157: =P157*(1-J157) | R157: =H157*K157 | S157: =IF(Q157=0,"",(Q157-R157)/Q157) | T157: =YEAR(B157) | U157: =YEAR(B157)&"-Q"&ROUNDUP(MONTH(B157)/3,0) | V157: =TEXT(B157,"YYYY-MM") | W157: =IF(L157="","",IF(L157>pLateDays,1,0)) | X157: =IF(Q157>=pHighCutoff,1,0) | Y157: =IF(M157="Returned",1,0)
A158: HC-100156 | B158: 45500 | C158: West | D158: Store | E158: Furniture | F158: Lounge Chair | G158: Consumer | H158: 1 | I158: 447.1 | J158: 0.07 | K158: 268.26 | L158: 5 | M158: Returned | N158: A. Shah | O158: No | P158: =H158*I158 | Q158: =P158*(1-J158) | R158: =H158*K158 | S158: =IF(Q158=0,"",(Q158-R158)/Q158) | T158: =YEAR(B158) | U158: =YEAR(B158)&"-Q"&ROUNDUP(MONTH(B158)/3,0) | V158: =TEXT(B158,"YYYY-MM") | W158: =IF(L158="","",IF(L158>pLateDays,1,0)) | X158: =IF(Q158>=pHighCutoff,1,0) | Y158: =IF(M158="Returned",1,0)
A159: HC-100157 | B159: 45649 | C159: West | D159: Store | E159: Kitchen | F159: Cast Skillet | G159: Consumer | H159: 4 | I159: 57.84 | J159: 0.03 | K159: 23.13 | L159: 6 | M159: Completed | N159: R. Ibarra | O159: No | P159: =H159*I159 | Q159: =P159*(1-J159) | R159: =H159*K159 | S159: =IF(Q159=0,"",(Q159-R159)/Q159) | T159: =YEAR(B159) | U159: =YEAR(B159)&"-Q"&ROUNDUP(MONTH(B159)/3,0) | V159: =TEXT(B159,"YYYY-MM") | W159: =IF(L159="","",IF(L159>pLateDays,1,0)) | X159: =IF(Q159>=pHighCutoff,1,0) | Y159: =IF(M159="Returned",1,0)
A160: HC-100158 | B160: 45728 | C160: West | D160: Online | E160: Textiles | F160: Wool Throw | G160: Consumer | H160: 2 | I160: 70.39 | J160: 0.03 | K160: 29.57 | L160: 7 | M160: Completed | N160: L. Berger | O160: No | P160: =H160*I160 | Q160: =P160*(1-J160) | R160: =H160*K160 | S160: =IF(Q160=0,"",(Q160-R160)/Q160) | T160: =YEAR(B160) | U160: =YEAR(B160)&"-Q"&ROUNDUP(MONTH(B160)/3,0) | V160: =TEXT(B160,"YYYY-MM") | W160: =IF(L160="","",IF(L160>pLateDays,1,0)) | X160: =IF(Q160>=pHighCutoff,1,0) | Y160: =IF(M160="Returned",1,0)
A161: HC-100159 | B161: 45728 | C161: East | D161: Store | E161: Lighting | F161: Arc Lamp | G161: Consumer | H161: 4 | I161: 294.85 | J161: 0 | K161: 141.53 | L161: 8 | M161: Completed | N161: S. Nguyen | O161: No | P161: =H161*I161 | Q161: =P161*(1-J161) | R161: =H161*K161 | S161: =IF(Q161=0,"",(Q161-R161)/Q161) | T161: =YEAR(B161) | U161: =YEAR(B161)&"-Q"&ROUNDUP(MONTH(B161)/3,0) | V161: =TEXT(B161,"YYYY-MM") | W161: =IF(L161="","",IF(L161>pLateDays,1,0)) | X161: =IF(Q161>=pHighCutoff,1,0) | Y161: =IF(M161="Returned",1,0)
A162: HC-100160 | B162: 45870 | C162: South | D162: Store | E162: Furniture | F162: Linen Sofa | G162: Consumer | H162: 3 | I162: 1155.67 | J162: 0.12 | K162: 762.74 | L162: 8 | M162: Completed | N162: P. Rossi | O162: No | P162: =H162*I162 | Q162: =P162*(1-J162) | R162: =H162*K162 | S162: =IF(Q162=0,"",(Q162-R162)/Q162) | T162: =YEAR(B162) | U162: =YEAR(B162)&"-Q"&ROUNDUP(MONTH(B162)/3,0) | V162: =TEXT(B162,"YYYY-MM") | W162: =IF(L162="","",IF(L162>pLateDays,1,0)) | X162: =IF(Q162>=pHighCutoff,1,0) | Y162: =IF(M162="Returned",1,0)
A163: HC-100161 | B163: 45618 | C163: East | D163: Store | E163: Lighting | F163: Arc Lamp | G163: Consumer | H163: 4 | I163: 267.04 | J163: 0.04 | K163: 128.18 | L163: 8 | M163: Completed | N163: A. Shah | O163: No | P163: =H163*I163 | Q163: =P163*(1-J163) | R163: =H163*K163 | S163: =IF(Q163=0,"",(Q163-R163)/Q163) | T163: =YEAR(B163) | U163: =YEAR(B163)&"-Q"&ROUNDUP(MONTH(B163)/3,0) | V163: =TEXT(B163,"YYYY-MM") | W163: =IF(L163="","",IF(L163>pLateDays,1,0)) | X163: =IF(Q163>=pHighCutoff,1,0) | Y163: =IF(M163="Returned",1,0)
A164: HC-100162 | B164: 45830 | C164: East | D164: Wholesale | E164: Furniture | F164: Walnut Shelf | G164: Consumer | H164: 28 | I164: 192.58 | J164: 0.23 | K164: 105.92 | L164: 8 | M164: Completed | N164: A. Shah | O164: No | P164: =H164*I164 | Q164: =P164*(1-J164) | R164: =H164*K164 | S164: =IF(Q164=0,"",(Q164-R164)/Q164) | T164: =YEAR(B164) | U164: =YEAR(B164)&"-Q"&ROUNDUP(MONTH(B164)/3,0) | V164: =TEXT(B164,"YYYY-MM") | W164: =IF(L164="","",IF(L164>pLateDays,1,0)) | X164: =IF(Q164>=pHighCutoff,1,0) | Y164: =IF(M164="Returned",1,0)
A165: HC-100163 | B165: 45742 | C165: North | D165: Store | E165: Kitchen | F165: Chef Knife | G165: Consumer | H165: 3 | I165: 68.12 | J165: 0.11 | K165: 24.52 | L165: 6 | M165: Completed | N165: K. Mensah | O165: No | P165: =H165*I165 | Q165: =P165*(1-J165) | R165: =H165*K165 | S165: =IF(Q165=0,"",(Q165-R165)/Q165) | T165: =YEAR(B165) | U165: =YEAR(B165)&"-Q"&ROUNDUP(MONTH(B165)/3,0) | V165: =TEXT(B165,"YYYY-MM") | W165: =IF(L165="","",IF(L165>pLateDays,1,0)) | X165: =IF(Q165>=pHighCutoff,1,0) | Y165: =IF(M165="Returned",1,0)
A166: HC-100164 | B166: 45635 | C166: South | D166: Online | E166: Lighting | F166: Brass Sconce | G166: Corporate | H166: 4 | I166: 149.68 | J166: 0.17 | K166: 68.85 | M166: Completed | N166: A. Shah | O166: No | P166: =H166*I166 | Q166: =P166*(1-J166) | R166: =H166*K166 | S166: =IF(Q166=0,"",(Q166-R166)/Q166) | T166: =YEAR(B166) | U166: =YEAR(B166)&"-Q"&ROUNDUP(MONTH(B166)/3,0) | V166: =TEXT(B166,"YYYY-MM") | W166: =IF(L166="","",IF(L166>pLateDays,1,0)) | X166: =IF(Q166>=pHighCutoff,1,0) | Y166: =IF(M166="Returned",1,0)
A167: HC-100165 | B167: 45683 | C167: North | D167: Online | E167: Textiles | F167: Linen Curtain | G167: Consumer | H167: 3 | I167: 100.38 | J167: 0.08 | K167: 45.17 | L167: 8 | M167: Completed | N167: S. Nguyen | O167: No | P167: =H167*I167 | Q167: =P167*(1-J167) | R167: =H167*K167 | S167: =IF(Q167=0,"",(Q167-R167)/Q167) | T167: =YEAR(B167) | U167: =YEAR(B167)&"-Q"&ROUNDUP(MONTH(B167)/3,0) | V167: =TEXT(B167,"YYYY-MM") | W167: =IF(L167="","",IF(L167>pLateDays,1,0)) | X167: =IF(Q167>=pHighCutoff,1,0) | Y167: =IF(M167="Returned",1,0)
A168: HC-100166 | B168: 45889 | C168: West | D168: Online | E168: Furniture | F168: Oak Desk | G168: Consumer | H168: 2 | I168: 842.8 | J168: 0.14 | K168: 522.54 | L168: 9 | M168: Completed | N168: K. Mensah | O168: No | P168: =H168*I168 | Q168: =P168*(1-J168) | R168: =H168*K168 | S168: =IF(Q168=0,"",(Q168-R168)/Q168) | T168: =YEAR(B168) | U168: =YEAR(B168)&"-Q"&ROUNDUP(MONTH(B168)/3,0) | V168: =TEXT(B168,"YYYY-MM") | W168: =IF(L168="","",IF(L168>pLateDays,1,0)) | X168: =IF(Q168>=pHighCutoff,1,0) | Y168: =IF(M168="Returned",1,0)
A169: HC-100167 | B169: 45652 | C169: North | D169: Store | E169: Kitchen | F169: Cast Skillet | G169: Consumer | H169: 4 | I169: 51.63 | J169: 0.11 | K169: 20.65 | L169: 3 | M169: Completed | N169: J. Patel | O169: No | P169: =H169*I169 | Q169: =P169*(1-J169) | R169: =H169*K169 | S169: =IF(Q169=0,"",(Q169-R169)/Q169) | T169: =YEAR(B169) | U169: =YEAR(B169)&"-Q"&ROUNDUP(MONTH(B169)/3,0) | V169: =TEXT(B169,"YYYY-MM") | W169: =IF(L169="","",IF(L169>pLateDays,1,0)) | X169: =IF(Q169>=pHighCutoff,1,0) | Y169: =IF(M169="Returned",1,0)
A170: HC-100168 | B170: 45671 | C170: West | D170: Online | E170: Kitchen | F170: Chef Knife | G170: Corporate | H170: 3 | I170: 67.2 | J170: 0.18 | K170: 24.19 | L170: 8 | M170: Completed | N170: M. Okonkwo | O170: No | P170: =H170*I170 | Q170: =P170*(1-J170) | R170: =H170*K170 | S170: =IF(Q170=0,"",(Q170-R170)/Q170) | T170: =YEAR(B170) | U170: =YEAR(B170)&"-Q"&ROUNDUP(MONTH(B170)/3,0) | V170: =TEXT(B170,"YYYY-MM") | W170: =IF(L170="","",IF(L170>pLateDays,1,0)) | X170: =IF(Q170>=pHighCutoff,1,0) | Y170: =IF(M170="Returned",1,0)
A171: HC-100169 | B171: 45787 | C171: West | D171: Store | E171: Textiles | F171: Cotton Duvet | G171: Consumer | H171: 4 | I171: 117.9 | J171: 0.1 | K171: 51.87 | L171: 5 | M171: Completed | N171: R. Ibarra | O171: No | P171: =H171*I171 | Q171: =P171*(1-J171) | R171: =H171*K171 | S171: =IF(Q171=0,"",(Q171-R171)/Q171) | T171: =YEAR(B171) | U171: =YEAR(B171)&"-Q"&ROUNDUP(MONTH(B171)/3,0) | V171: =TEXT(B171,"YYYY-MM") | W171: =IF(L171="","",IF(L171>pLateDays,1,0)) | X171: =IF(Q171>=pHighCutoff,1,0) | Y171: =IF(M171="Returned",1,0)
A172: HC-100170 | B172: 45383 | C172: North | D172: Wholesale | E172: Furniture | F172: Walnut Shelf | G172: Consumer | H172: 22 | I172: 209.4 | J172: 0.17 | K172: 115.17 | L172: 6 | M172: Completed | N172: M. Okonkwo | O172: No | P172: =H172*I172 | Q172: =P172*(1-J172) | R172: =H172*K172 | S172: =IF(Q172=0,"",(Q172-R172)/Q172) | T172: =YEAR(B172) | U172: =YEAR(B172)&"-Q"&ROUNDUP(MONTH(B172)/3,0) | V172: =TEXT(B172,"YYYY-MM") | W172: =IF(L172="","",IF(L172>pLateDays,1,0)) | X172: =IF(Q172>=pHighCutoff,1,0) | Y172: =IF(M172="Returned",1,0)
A173: HC-100171 | B173: 45496 | C173: West | D173: Online | E173: Textiles | F173: Cotton Duvet | G173: Home Office | H173: 3 | I173: 122.74 | J173: 0.13 | K173: 54.01 | L173: 9 | M173: Completed | N173: J. Patel | O173: No | P173: =H173*I173 | Q173: =P173*(1-J173) | R173: =H173*K173 | S173: =IF(Q173=0,"",(Q173-R173)/Q173) | T173: =YEAR(B173) | U173: =YEAR(B173)&"-Q"&ROUNDUP(MONTH(B173)/3,0) | V173: =TEXT(B173,"YYYY-MM") | W173: =IF(L173="","",IF(L173>pLateDays,1,0)) | X173: =IF(Q173>=pHighCutoff,1,0) | Y173: =IF(M173="Returned",1,0)
A174: HC-100172 | B174: 45828 | C174: North | D174: Online | E174: Lighting | F174: Arc Lamp | G174: Consumer | H174: 1 | I174: 327.82 | J174: 0.06 | K174: 157.35 | L174: 3 | M174: Completed | N174: R. Ibarra | O174: No | P174: =H174*I174 | Q174: =P174*(1-J174) | R174: =H174*K174 | S174: =IF(Q174=0,"",(Q174-R174)/Q174) | T174: =YEAR(B174) | U174: =YEAR(B174)&"-Q"&ROUNDUP(MONTH(B174)/3,0) | V174: =TEXT(B174,"YYYY-MM") | W174: =IF(L174="","",IF(L174>pLateDays,1,0)) | X174: =IF(Q174>=pHighCutoff,1,0) | Y174: =IF(M174="Returned",1,0)
A175: HC-100173 | B175: 45578 | C175: North | D175: Store | E175: Lighting | F175: Arc Lamp | G175: Corporate | H175: 3 | I175: 315.5 | J175: 0.04 | K175: 151.44 | L175: 4 | M175: Completed | N175: K. Mensah | O175: No | P175: =H175*I175 | Q175: =P175*(1-J175) | R175: =H175*K175 | S175: =IF(Q175=0,"",(Q175-R175)/Q175) | T175: =YEAR(B175) | U175: =YEAR(B175)&"-Q"&ROUNDUP(MONTH(B175)/3,0) | V175: =TEXT(B175,"YYYY-MM") | W175: =IF(L175="","",IF(L175>pLateDays,1,0)) | X175: =IF(Q175>=pHighCutoff,1,0) | Y175: =IF(M175="Returned",1,0)
A176: HC-100174 | B176: 45532 | C176: West | D176: Online | E176: Lighting | F176: Brass Sconce | G176: Consumer | H176: 1 | I176: 130.87 | J176: 0.12 | K176: 60.2 | L176: 5 | M176: Completed | N176: L. Berger | O176: No | P176: =H176*I176 | Q176: =P176*(1-J176) | R176: =H176*K176 | S176: =IF(Q176=0,"",(Q176-R176)/Q176) | T176: =YEAR(B176) | U176: =YEAR(B176)&"-Q"&ROUNDUP(MONTH(B176)/3,0) | V176: =TEXT(B176,"YYYY-MM") | W176: =IF(L176="","",IF(L176>pLateDays,1,0)) | X176: =IF(Q176>=pHighCutoff,1,0) | Y176: =IF(M176="Returned",1,0)
A177: HC-100175 | B177: 45579 | C177: West | D177: Wholesale | E177: Textiles | F177: Linen Curtain | G177: Corporate | H177: 35 | I177: 100.35 | J177: 0.27 | K177: 45.16 | L177: 7 | M177: Returned | N177: K. Mensah | O177: No | P177: =H177*I177 | Q177: =P177*(1-J177) | R177: =H177*K177 | S177: =IF(Q177=0,"",(Q177-R177)/Q177) | T177: =YEAR(B177) | U177: =YEAR(B177)&"-Q"&ROUNDUP(MONTH(B177)/3,0) | V177: =TEXT(B177,"YYYY-MM") | W177: =IF(L177="","",IF(L177>pLateDays,1,0)) | X177: =IF(Q177>=pHighCutoff,1,0) | Y177: =IF(M177="Returned",1,0)
A178: HC-100176 | B178: 45745 | C178: West | D178: Wholesale | E178: Kitchen | F178: Chef Knife | G178: Corporate | H178: 24 | I178: 60.59 | J178: 0.24 | K178: 21.81 | L178: 6 | M178: Cancelled | N178: J. Patel | O178: No | P178: =H178*I178 | Q178: =P178*(1-J178) | R178: =H178*K178 | S178: =IF(Q178=0,"",(Q178-R178)/Q178) | T178: =YEAR(B178) | U178: =YEAR(B178)&"-Q"&ROUNDUP(MONTH(B178)/3,0) | V178: =TEXT(B178,"YYYY-MM") | W178: =IF(L178="","",IF(L178>pLateDays,1,0)) | X178: =IF(Q178>=pHighCutoff,1,0) | Y178: =IF(M178="Returned",1,0)
... A183: HC-100181 | B183: 45476 | C183: East | D183: Store | E183: Kitchen | F183: Chef Knife | G183: Corporate | H183: 2 | I183: 58.92 | J183: 0.08 | K183: 21.21 | L183: 8 | M183: Completed | N183: L. Berger | O183: No | P183: =H183*I183 | Q183: =P183*(1-J183) | R183: =H183*K183 | S183: =IF(Q183=0,"",(Q183-R183)/Q183) | T183: =YEAR(B183) | U183: =YEAR(B183)&"-Q"&ROUNDUP(MONTH(B183)/3,0) | V183: =TEXT(B183,"YYYY-MM") | W183: =IF(L183="","",IF(L183>pLateDays,1,0)) | X183: =IF(Q183>=pHighCutoff,1,0) | Y183: =IF(M183="Returned",1,0)
A184: HC-100182 | B184: 45586 | C184: North | D184: Online | E184: Furniture | F184: Walnut Shelf | G184: Consumer | H184: 3 | I184: 235.81 | J184: 0.07 | K184: 129.7 | M184: Completed | N184: P. Rossi | O184: No | P184: =H184*I184 | Q184: =P184*(1-J184) | R184: =H184*K184 | S184: =IF(Q184=0,"",(Q184-R184)/Q184) | T184: =YEAR(B184) | U184: =YEAR(B184)&"-Q"&ROUNDUP(MONTH(B184)/3,0) | V184: =TEXT(B184,"YYYY-MM") | W184: =IF(L184="","",IF(L184>pLateDays,1,0)) | X184: =IF(Q184>=pHighCutoff,1,0) | Y184: =IF(M184="Returned",1,0)
A185: HC-100183 | B185: 45317 | C185: West | D185: Wholesale | E185: Textiles | F185: Cotton Duvet | G185: Home Office | H185: 32 | I185: 111.15 | J185: 0.31 | K185: 48.91 | L185: 3 | M185: Cancelled | N185: R. Ibarra | O185: No | P185: =H185*I185 | Q185: =P185*(1-J185) | R185: =H185*K185 | S185: =IF(Q185=0,"",(Q185-R185)/Q185) | T185: =YEAR(B185) | U185: =YEAR(B185)&"-Q"&ROUNDUP(MONTH(B185)/3,0) | V185: =TEXT(B185,"YYYY-MM") | W185: =IF(L185="","",IF(L185>pLateDays,1,0)) | X185: =IF(Q185>=pHighCutoff,1,0) | Y185: =IF(M185="Returned",1,0)
A186: HC-100184 | B186: 45417 | C186: North | D186: Online | E186: Textiles | F186: Wool Throw | G186: Consumer | H186: 2 | I186: 77.02 | J186: 0.08 | K186: 32.35 | L186: 5 | M186: Completed | N186: P. Rossi | O186: No | P186: =H186*I186 | Q186: =P186*(1-J186) | R186: =H186*K186 | S186: =IF(Q186=0,"",(Q186-R186)/Q186) | T186: =YEAR(B186) | U186: =YEAR(B186)&"-Q"&ROUNDUP(MONTH(B186)/3,0) | V186: =TEXT(B186,"YYYY-MM") | W186: =IF(L186="","",IF(L186>pLateDays,1,0)) | X186: =IF(Q186>=pHighCutoff,1,0) | Y186: =IF(M186="Returned",1,0)
A187: HC-100185 | B187: 45468 | C187: West | D187: Store | E187: Kitchen | F187: Ceramic Set | G187: Home Office | H187: 1 | I187: 86.5 | J187: 0.07 | K187: 32.87 | L187: 5 | M187: Completed | N187: P. Rossi | O187: No | P187: =H187*I187 | Q187: =P187*(1-J187) | R187: =H187*K187 | S187: =IF(Q187=0,"",(Q187-R187)/Q187) | T187: =YEAR(B187) | U187: =YEAR(B187)&"-Q"&ROUNDUP(MONTH(B187)/3,0) | V187: =TEXT(B187,"YYYY-MM") | W187: =IF(L187="","",IF(L187>pLateDays,1,0)) | X187: =IF(Q187>=pHighCutoff,1,0) | Y187: =IF(M187="Returned",1,0)
A188: HC-100186 | B188: 45438 | C188: East | D188: Store | E188: Kitchen | F188: Ceramic Set | G188: Home Office | H188: 2 | I188: 82.05 | J188: 0.01 | K188: 31.18 | L188: 9 | M188: Completed | N188: M. Okonkwo | O188: No | P188: =H188*I188 | Q188: =P188*(1-J188) | R188: =H188*K188 | S188: =IF(Q188=0,"",(Q188-R188)/Q188) | T188: =YEAR(B188) | U188: =YEAR(B188)&"-Q"&ROUNDUP(MONTH(B188)/3,0) | V188: =TEXT(B188,"YYYY-MM") | W188: =IF(L188="","",IF(L188>pLateDays,1,0)) | X188: =IF(Q188>=pHighCutoff,1,0) | Y188: =IF(M188="Returned",1,0)
A189: HC-100187 | B189: 45492 | C189: South | D189: Store | E189: Lighting | F189: Pendant Light | G189: Consumer | H189: 1 | I189: 169.73 | J189: 0.05 | K189: 84.86 | L189: 6 | M189: Returned | N189: P. Rossi | O189: No | P189: =H189*I189 | Q189: =P189*(1-J189) | R189: =H189*K189 | S189: =IF(Q189=0,"",(Q189-R189)/Q189) | T189: =YEAR(B189) | U189: =YEAR(B189)&"-Q"&ROUNDUP(MONTH(B189)/3,0) | V189: =TEXT(B189,"YYYY-MM") | W189: =IF(L189="","",IF(L189>pLateDays,1,0)) | X189: =IF(Q189>=pHighCutoff,1,0) | Y189: =IF(M189="Returned",1,0)
A190: HC-100188 | B190: 45365 | C190: South | D190: Wholesale | E190: Kitchen | F190: Ceramic Set | G190: Consumer | H190: 32 | I190: 80.23 | J190: 0.2 | K190: 30.49 | L190: 2 | M190: Completed | N190: J. Patel | O190: No | P190: =H190*I190 | Q190: =P190*(1-J190) | R190: =H190*K190 | S190: =IF(Q190=0,"",(Q190-R190)/Q190) | T190: =YEAR(B190) | U190: =YEAR(B190)&"-Q"&ROUNDUP(MONTH(B190)/3,0) | V190: =TEXT(B190,"YYYY-MM") | W190: =IF(L190="","",IF(L190>pLateDays,1,0)) | X190: =IF(Q190>=pHighCutoff,1,0) | Y190: =IF(M190="Returned",1,0)
A191: HC-100189 | B191: 45620 | C191: North | D191: Online | E191: Furniture | F191: Oak Desk | G191: Consumer | H191: 4 | I191: 778.58 | J191: 0.17 | K191: 482.72 | L191: 7 | M191: Completed | N191: M. Okonkwo | O191: No | P191: =H191*I191 | Q191: =P191*(1-J191) | R191: =H191*K191 | S191: =IF(Q191=0,"",(Q191-R191)/Q191) | T191: =YEAR(B191) | U191: =YEAR(B191)&"-Q"&ROUNDUP(MONTH(B191)/3,0) | V191: =TEXT(B191,"YYYY-MM") | W191: =IF(L191="","",IF(L191>pLateDays,1,0)) | X191: =IF(Q191>=pHighCutoff,1,0) | Y191: =IF(M191="Returned",1,0)
A192: HC-100190 | B192: 45618 | C192: West | D192: Online | E192: Lighting | F192: Brass Sconce | G192: Corporate | H192: 3 | I192: 131.58 | J192: 0.11 | K192: 60.53 | L192: 7 | M192: Completed | N192: S. Nguyen | O192: No | P192: =H192*I192 | Q192: =P192*(1-J192) | R192: =H192*K192 | S192: =IF(Q192=0,"",(Q192-R192)/Q192) | T192: =YEAR(B192) | U192: =YEAR(B192)&"-Q"&ROUNDUP(MONTH(B192)/3,0) | V192: =TEXT(B192,"YYYY-MM") | W192: =IF(L192="","",IF(L192>pLateDays,1,0)) | X192: =IF(Q192>=pHighCutoff,1,0) | Y192: =IF(M192="Returned",1,0)
A193: HC-100191 | B193: 45759 | C193: West | D193: Online | E193: Textiles | F193: Cotton Duvet | G193: Consumer | H193: 2 | I193: 126.71 | J193: 0.15 | K193: 55.75 | L193: 5 | M193: Completed | N193: R. Ibarra | O193: No | P193: =H193*I193 | Q193: =P193*(1-J193) | R193: =H193*K193 | S193: =IF(Q193=0,"",(Q193-R193)/Q193) | T193: =YEAR(B193) | U193: =YEAR(B193)&"-Q"&ROUNDUP(MONTH(B193)/3,0) | V193: =TEXT(B193,"YYYY-MM") | W193: =IF(L193="","",IF(L193>pLateDays,1,0)) | X193: =IF(Q193>=pHighCutoff,1,0) | Y193: =IF(M193="Returned",1,0)
A194: HC-100192 | B194: 45548 | C194: South | D194: Store | E194: Furniture | F194: Walnut Shelf | G194: Consumer | H194: 4 | I194: 222.6 | J194: 0.08 | K194: 122.43 | L194: 4 | M194: Completed | N194: R. Ibarra | O194: No | P194: =H194*I194 | Q194: =P194*(1-J194) | R194: =H194*K194 | S194: =IF(Q194=0,"",(Q194-R194)/Q194) | T194: =YEAR(B194) | U194: =YEAR(B194)&"-Q"&ROUNDUP(MONTH(B194)/3,0) | V194: =TEXT(B194,"YYYY-MM") | W194: =IF(L194="","",IF(L194>pLateDays,1,0)) | X194: =IF(Q194>=pHighCutoff,1,0) | Y194: =IF(M194="Returned",1,0)
A195: HC-100193 | B195: 45830 | C195: North | D195: Store | E195: Furniture | F195: Oak Desk | G195: Corporate | H195: 3 | I195: 865.1 | J195: 0.07 | K195: 536.36 | L195: 5 | M195: Completed | N195: R. Ibarra | O195: No | P195: =H195*I195 | Q195: =P195*(1-J195) | R195: =H195*K195 | S195: =IF(Q195=0,"",(Q195-R195)/Q195) | T195: =YEAR(B195) | U195: =YEAR(B195)&"-Q"&ROUNDUP(MONTH(B195)/3,0) | V195: =TEXT(B195,"YYYY-MM") | W195: =IF(L195="","",IF(L195>pLateDays,1,0)) | X195: =IF(Q195>=pHighCutoff,1,0) | Y195: =IF(M195="Returned",1,0)
A196: HC-100194 | B196: 45607 | C196: North | D196: Online | E196: Kitchen | F196: Cast Skillet | G196: Consumer | H196: 4 | I196: 57.9 | J196: 0.1 | K196: 23.16 | L196: 5 | M196: Completed | N196: L. Berger | O196: No | P196: =H196*I196 | Q196: =P196*(1-J196) | R196: =H196*K196 | S196: =IF(Q196=0,"",(Q196-R196)/Q196) | T196: =YEAR(B196) | U196: =YEAR(B196)&"-Q"&ROUNDUP(MONTH(B196)/3,0) | V196: =TEXT(B196,"YYYY-MM") | W196: =IF(L196="","",IF(L196>pLateDays,1,0)) | X196: =IF(Q196>=pHighCutoff,1,0) | Y196: =IF(M196="Returned",1,0)
... A226: HC-100224 | B226: 45537 | C226: South | D226: Wholesale | E226: Textiles | F226: Cotton Duvet | G226: Consumer | H226: 19 | I226: 111.65 | J226: 0.32 | K226: 49.13 | L226: 5 | M226: Returned | N226: R. Ibarra | O226: No | P226: =H226*I226 | Q226: =P226*(1-J226) | R226: =H226*K226 | S226: =IF(Q226=0,"",(Q226-R226)/Q226) | T226: =YEAR(B226) | U226: =YEAR(B226)&"-Q"&ROUNDUP(MONTH(B226)/3,0) | V226: =TEXT(B226,"YYYY-MM") | W226: =IF(L226="","",IF(L226>pLateDays,1,0)) | X226: =IF(Q226>=pHighCutoff,1,0) | Y226: =IF(M226="Returned",1,0)
A227: HC-100225 | B227: 45320 | C227: South | D227: Store | E227: Furniture | F227: Linen Sofa | G227: Home Office | H227: 2 | I227: 1205.13 | J227: 0.01 | K227: 795.39 | M227: Completed | N227: J. Patel | O227: No | P227: =H227*I227 | Q227: =P227*(1-J227) | R227: =H227*K227 | S227: =IF(Q227=0,"",(Q227-R227)/Q227) | T227: =YEAR(B227) | U227: =YEAR(B227)&"-Q"&ROUNDUP(MONTH(B227)/3,0) | V227: =TEXT(B227,"YYYY-MM") | W227: =IF(L227="","",IF(L227>pLateDays,1,0)) | X227: =IF(Q227>=pHighCutoff,1,0) | Y227: =IF(M227="Returned",1,0)
A228: HC-100226 | B228: 45928 | C228: South | D228: Store | E228: Furniture | F228: Linen Sofa | G228: Consumer | H228: 2 | I228: 1301.6 | J228: 0.1 | K228: 859.06 | L228: 4 | M228: Completed | N228: L. Berger | O228: No | P228: =H228*I228 | Q228: =P228*(1-J228) | R228: =H228*K228 | S228: =IF(Q228=0,"",(Q228-R228)/Q228) | T228: =YEAR(B228) | U228: =YEAR(B228)&"-Q"&ROUNDUP(MONTH(B228)/3,0) | V228: =TEXT(B228,"YYYY-MM") | W228: =IF(L228="","",IF(L228>pLateDays,1,0)) | X228: =IF(Q228>=pHighCutoff,1,0) | Y228: =IF(M228="Returned",1,0)
A229: HC-100227 | B229: 45580 | C229: North | D229: Store | E229: Lighting | F229: Brass Sconce | G229: Corporate | H229: 3 | I229: 144.81 | J229: 0.07 | K229: 66.61 | L229: 7 | M229: Completed | N229: J. Patel | O229: No | P229: =H229*I229 | Q229: =P229*(1-J229) | R229: =H229*K229 | S229: =IF(Q229=0,"",(Q229-R229)/Q229) | T229: =YEAR(B229) | U229: =YEAR(B229)&"-Q"&ROUNDUP(MONTH(B229)/3,0) | V229: =TEXT(B229,"YYYY-MM") | W229: =IF(L229="","",IF(L229>pLateDays,1,0)) | X229: =IF(Q229>=pHighCutoff,1,0) | Y229: =IF(M229="Returned",1,0)
A230: HC-100228 | B230: 45835 | C230: North | D230: Store | E230: Furniture | F230: Oak Desk | G230: Consumer | H230: 1 | I230: 809.75 | J230: 0.05 | K230: 502.05 | L230: 5 | M230: Completed | N230: J. Patel | O230: No | P230: =H230*I230 | Q230: =P230*(1-J230) | R230: =H230*K230 | S230: =IF(Q230=0,"",(Q230-R230)/Q230) | T230: =YEAR(B230) | U230: =YEAR(B230)&"-Q"&ROUNDUP(MONTH(B230)/3,0) | V230: =TEXT(B230,"YYYY-MM") | W230: =IF(L230="","",IF(L230>pLateDays,1,0)) | X230: =IF(Q230>=pHighCutoff,1,0) | Y230: =IF(M230="Returned",1,0)
A231: HC-100229 | B231: 45677 | C231: North | D231: Online | E231: Kitchen | F231: Ceramic Set | G231: Consumer | H231: 1 | I231: 88.23 | J231: 0.14 | K231: 33.53 | L231: 3 | M231: Completed | N231: L. Berger | O231: No | P231: =H231*I231 | Q231: =P231*(1-J231) | R231: =H231*K231 | S231: =IF(Q231=0,"",(Q231-R231)/Q231) | T231: =YEAR(B231) | U231: =YEAR(B231)&"-Q"&ROUNDUP(MONTH(B231)/3,0) | V231: =TEXT(B231,"YYYY-MM") | W231: =IF(L231="","",IF(L231>pLateDays,1,0)) | X231: =IF(Q231>=pHighCutoff,1,0) | Y231: =IF(M231="Returned",1,0)
A232: HC-100230 | B232: 45562 | C232: North | D232: Online | E232: Textiles | F232: Cotton Duvet | G232: Consumer | H232: 2 | I232: 126.63 | J232: 0.16 | K232: 55.72 | L232: 9 | M232: Completed | N232: L. Berger | O232: No | P232: =H232*I232 | Q232: =P232*(1-J232) | R232: =H232*K232 | S232: =IF(Q232=0,"",(Q232-R232)/Q232) | T232: =YEAR(B232) | U232: =YEAR(B232)&"-Q"&ROUNDUP(MONTH(B232)/3,0) | V232: =TEXT(B232,"YYYY-MM") | W232: =IF(L232="","",IF(L232>pLateDays,1,0)) | X232: =IF(Q232>=pHighCutoff,1,0) | Y232: =IF(M232="Returned",1,0)
A233: HC-100231 | B233: 45800 | C233: South | D233: Store | E233: Kitchen | F233: Chef Knife | G233: Consumer | H233: 1 | I233: 67.89 | J233: 0.07 | K233: 24.44 | L233: 7 | M233: Completed | N233: P. Rossi | O233: No | P233: =H233*I233 | Q233: =P233*(1-J233) | R233: =H233*K233 | S233: =IF(Q233=0,"",(Q233-R233)/Q233) | T233: =YEAR(B233) | U233: =YEAR(B233)&"-Q"&ROUNDUP(MONTH(B233)/3,0) | V233: =TEXT(B233,"YYYY-MM") | W233: =IF(L233="","",IF(L233>pLateDays,1,0)) | X233: =IF(Q233>=pHighCutoff,1,0) | Y233: =IF(M233="Returned",1,0)
A234: HC-100232 | B234: 45427 | C234: North | D234: Wholesale | E234: Lighting | F234: Arc Lamp | G234: Corporate | H234: 17 | I234: 309.25 | J234: 0.16 | K234: 148.44 | L234: 4 | M234: Completed | N234: K. Mensah | O234: No | P234: =H234*I234 | Q234: =P234*(1-J234) | R234: =H234*K234 | S234: =IF(Q234=0,"",(Q234-R234)/Q234) | T234: =YEAR(B234) | U234: =YEAR(B234)&"-Q"&ROUNDUP(MONTH(B234)/3,0) | V234: =TEXT(B234,"YYYY-MM") | W234: =IF(L234="","",IF(L234>pLateDays,1,0)) | X234: =IF(Q234>=pHighCutoff,1,0) | Y234: =IF(M234="Returned",1,0)
A235: HC-100233 | B235: 45341 | C235: East | D235: Wholesale | E235: Textiles | F235: Cotton Duvet | G235: Consumer | H235: 30 | I235: 112.89 | J235: 0.24 | K235: 49.67 | L235: 11 | M235: Completed | N235: L. Berger | O235: No | P235: =H235*I235 | Q235: =P235*(1-J235) | R235: =H235*K235 | S235: =IF(Q235=0,"",(Q235-R235)/Q235) | T235: =YEAR(B235) | U235: =YEAR(B235)&"-Q"&ROUNDUP(MONTH(B235)/3,0) | V235: =TEXT(B235,"YYYY-MM") | W235: =IF(L235="","",IF(L235>pLateDays,1,0)) | X235: =IF(Q235>=pHighCutoff,1,0) | Y235: =IF(M235="Returned",1,0)
A236: HC-100234 | B236: 45414 | C236: North | D236: Store | E236: Furniture | F236: Linen Sofa | G236: Consumer | H236: 1 | I236: 1156.23 | J236: 0.04 | K236: 763.11 | L236: 6 | M236: Completed | N236: L. Berger | O236: No | P236: =H236*I236 | Q236: =P236*(1-J236) | R236: =H236*K236 | S236: =IF(Q236=0,"",(Q236-R236)/Q236) | T236: =YEAR(B236) | U236: =YEAR(B236)&"-Q"&ROUNDUP(MONTH(B236)/3,0) | V236: =TEXT(B236,"YYYY-MM") | W236: =IF(L236="","",IF(L236>pLateDays,1,0)) | X236: =IF(Q236>=pHighCutoff,1,0) | Y236: =IF(M236="Returned",1,0)
A237: HC-100235 | B237: 45529 | C237: South | D237: Store | E237: Textiles | F237: Wool Throw | G237: Corporate | H237: 3 | I237: 70.24 | J237: 0.11 | K237: 29.5 | L237: 3 | M237: Completed | N237: M. Okonkwo | O237: No | P237: =H237*I237 | Q237: =P237*(1-J237) | R237: =H237*K237 | S237: =IF(Q237=0,"",(Q237-R237)/Q237) | T237: =YEAR(B237) | U237: =YEAR(B237)&"-Q"&ROUNDUP(MONTH(B237)/3,0) | V237: =TEXT(B237,"YYYY-MM") | W237: =IF(L237="","",IF(L237>pLateDays,1,0)) | X237: =IF(Q237>=pHighCutoff,1,0) | Y237: =IF(M237="Returned",1,0)
A238: HC-100236 | B238: 45442 | C238: South | D238: Online | E238: Textiles | F238: Wool Throw | G238: Corporate | H238: 3 | I238: 71.82 | J238: 0.08 | K238: 30.16 | L238: 3 | M238: Completed | N238: P. Rossi | O238: No | P238: =H238*I238 | Q238: =P238*(1-J238) | R238: =H238*K238 | S238: =IF(Q238=0,"",(Q238-R238)/Q238) | T238: =YEAR(B238) | U238: =YEAR(B238)&"-Q"&ROUNDUP(MONTH(B238)/3,0) | V238: =TEXT(B238,"YYYY-MM") | W238: =IF(L238="","",IF(L238>pLateDays,1,0)) | X238: =IF(Q238>=pHighCutoff,1,0) | Y238: =IF(M238="Returned",1,0)
A239: HC-100237 | B239: 45667 | C239: South | D239: Store | E239: Textiles | F239: Cotton Duvet | G239: Consumer | H239: 1 | I239: 126.75 | J239: 0 | K239: 55.77 | L239: 6 | M239: Completed | N239: M. Okonkwo | O239: No | P239: =H239*I239 | Q239: =P239*(1-J239) | R239: =H239*K239 | S239: =IF(Q239=0,"",(Q239-R239)/Q239) | T239: =YEAR(B239) | U239: =YEAR(B239)&"-Q"&ROUNDUP(MONTH(B239)/3,0) | V239: =TEXT(B239,"YYYY-MM") | W239: =IF(L239="","",IF(L239>pLateDays,1,0)) | X239: =IF(Q239>=pHighCutoff,1,0) | Y239: =IF(M239="Returned",1,0)
... A311: HC-100309 | B311: 45540 | C311: North | D311: Wholesale | E311: Lighting | F311: Brass Sconce | G311: Corporate | H311: 27 | I311: 140.04 | J311: 0.24 | K311: 64.42 | L311: 5 | M311: Completed | N311: A. Shah | O311: No | P311: =H311*I311 | Q311: =P311*(1-J311) | R311: =H311*K311 | S311: =IF(Q311=0,"",(Q311-R311)/Q311) | T311: =YEAR(B311) | U311: =YEAR(B311)&"-Q"&ROUNDUP(MONTH(B311)/3,0) | V311: =TEXT(B311,"YYYY-MM") | W311: =IF(L311="","",IF(L311>pLateDays,1,0)) | X311: =IF(Q311>=pHighCutoff,1,0) | Y311: =IF(M311="Returned",1,0)
A312: HC-100310 | B312: 45643 | C312: West | D312: Store | E312: Lighting | F312: Brass Sconce | G312: Consumer | H312: 3 | I312: 150.45 | J312: 0 | K312: 69.21 | M312: Completed | N312: P. Rossi | O312: No | P312: =H312*I312 | Q312: =P312*(1-J312) | R312: =H312*K312 | S312: =IF(Q312=0,"",(Q312-R312)/Q312) | T312: =YEAR(B312) | U312: =YEAR(B312)&"-Q"&ROUNDUP(MONTH(B312)/3,0) | V312: =TEXT(B312,"YYYY-MM") | W312: =IF(L312="","",IF(L312>pLateDays,1,0)) | X312: =IF(Q312>=pHighCutoff,1,0) | Y312: =IF(M312="Returned",1,0)
A313: HC-100311 | B313: 45495 | C313: North | D313: Online | E313: Furniture | F313: Walnut Shelf | G313: Consumer | H313: 3 | I313: 206.22 | J313: 0.06 | K313: 113.42 | M313: Completed | N313: R. Ibarra | O313: No | P313: =H313*I313 | Q313: =P313*(1-J313) | R313: =H313*K313 | S313: =IF(Q313=0,"",(Q313-R313)/Q313) | T313: =YEAR(B313) | U313: =YEAR(B313)&"-Q"&ROUNDUP(MONTH(B313)/3,0) | V313: =TEXT(B313,"YYYY-MM") | W313: =IF(L313="","",IF(L313>pLateDays,1,0)) | X313: =IF(Q313>=pHighCutoff,1,0) | Y313: =IF(M313="Returned",1,0)
A314: HC-100312 | B314: 45304 | C314: West | D314: Online | E314: Textiles | F314: Cotton Duvet | G314: Consumer | H314: 1 | I314: 123.4 | J314: 0.13 | K314: 54.3 | L314: 6 | M314: Completed | N314: M. Okonkwo | O314: No | P314: =H314*I314 | Q314: =P314*(1-J314) | R314: =H314*K314 | S314: =IF(Q314=0,"",(Q314-R314)/Q314) | T314: =YEAR(B314) | U314: =YEAR(B314)&"-Q"&ROUNDUP(MONTH(B314)/3,0) | V314: =TEXT(B314,"YYYY-MM") | W314: =IF(L314="","",IF(L314>pLateDays,1,0)) | X314: =IF(Q314>=pHighCutoff,1,0) | Y314: =IF(M314="Returned",1,0)
A315: HC-100313 | B315: 45373 | C315: North | D315: Wholesale | E315: Furniture | F315: Walnut Shelf | G315: Consumer | H315: 26 | I315: 225.96 | J315: 0.32 | K315: 124.28 | L315: 5 | M315: Completed | N315: M. Okonkwo | O315: No | P315: =H315*I315 | Q315: =P315*(1-J315) | R315: =H315*K315 | S315: =IF(Q315=0,"",(Q315-R315)/Q315) | T315: =YEAR(B315) | U315: =YEAR(B315)&"-Q"&ROUNDUP(MONTH(B315)/3,0) | V315: =TEXT(B315,"YYYY-MM") | W315: =IF(L315="","",IF(L315>pLateDays,1,0)) | X315: =IF(Q315>=pHighCutoff,1,0) | Y315: =IF(M315="Returned",1,0)
A316: HC-100314 | B316: 45826 | C316: South | D316: Store | E316: Kitchen | F316: Ceramic Set | G316: Consumer | H316: 2 | I316: 86.14 | J316: 0.04 | K316: 32.73 | L316: 4 | M316: Completed | N316: L. Berger | O316: No | P316: =H316*I316 | Q316: =P316*(1-J316) | R316: =H316*K316 | S316: =IF(Q316=0,"",(Q316-R316)/Q316) | T316: =YEAR(B316) | U316: =YEAR(B316)&"-Q"&ROUNDUP(MONTH(B316)/3,0) | V316: =TEXT(B316,"YYYY-MM") | W316: =IF(L316="","",IF(L316>pLateDays,1,0)) | X316: =IF(Q316>=pHighCutoff,1,0) | Y316: =IF(M316="Returned",1,0)
A317: HC-100315 | B317: 45849 | C317: South | D317: Store | E317: Furniture | F317: Walnut Shelf | G317: Consumer | H317: 1 | I317: 218.46 | J317: 0.1 | K317: 120.15 | L317: 8 | M317: Completed | N317: J. Patel | O317: No | P317: =H317*I317 | Q317: =P317*(1-J317) | R317: =H317*K317 | S317: =IF(Q317=0,"",(Q317-R317)/Q317) | T317: =YEAR(B317) | U317: =YEAR(B317)&"-Q"&ROUNDUP(MONTH(B317)/3,0) | V317: =TEXT(B317,"YYYY-MM") | W317: =IF(L317="","",IF(L317>pLateDays,1,0)) | X317: =IF(Q317>=pHighCutoff,1,0) | Y317: =IF(M317="Returned",1,0)
A318: HC-100316 | B318: 45671 | C318: North | D318: Wholesale | E318: Furniture | F318: Oak Desk | G318: Corporate | H318: 10 | I318: 885.58 | J318: 0.25 | K318: 549.06 | L318: 4 | M318: Completed | N318: P. Rossi | O318: No | P318: =H318*I318 | Q318: =P318*(1-J318) | R318: =H318*K318 | S318: =IF(Q318=0,"",(Q318-R318)/Q318) | T318: =YEAR(B318) | U318: =YEAR(B318)&"-Q"&ROUNDUP(MONTH(B318)/3,0) | V318: =TEXT(B318,"YYYY-MM") | W318: =IF(L318="","",IF(L318>pLateDays,1,0)) | X318: =IF(Q318>=pHighCutoff,1,0) | Y318: =IF(M318="Returned",1,0)
A319: HC-100317 | B319: 45647 | C319: East | D319: Wholesale | E319: Kitchen | F319: Cast Skillet | G319: Consumer | H319: 24 | I319: 44.83 | J319: 0.32 | K319: 17.93 | L319: 7 | M319: Completed | N319: A. Shah | O319: No | P319: =H319*I319 | Q319: =P319*(1-J319) | R319: =H319*K319 | S319: =IF(Q319=0,"",(Q319-R319)/Q319) | T319: =YEAR(B319) | U319: =YEAR(B319)&"-Q"&ROUNDUP(MONTH(B319)/3,0) | V319: =TEXT(B319,"YYYY-MM") | W319: =IF(L319="","",IF(L319>pLateDays,1,0)) | X319: =IF(Q319>=pHighCutoff,1,0) | Y319: =IF(M319="Returned",1,0)
A320: HC-100318 | B320: 45292 | C320: North | D320: Online | E320: Kitchen | F320: Chef Knife | G320: Consumer | H320: 2 | I320: 67.06 | J320: 0.03 | K320: 24.14 | L320: 6 | M320: Completed | N320: J. Patel | O320: No | P320: =H320*I320 | Q320: =P320*(1-J320) | R320: =H320*K320 | S320: =IF(Q320=0,"",(Q320-R320)/Q320) | T320: =YEAR(B320) | U320: =YEAR(B320)&"-Q"&ROUNDUP(MONTH(B320)/3,0) | V320: =TEXT(B320,"YYYY-MM") | W320: =IF(L320="","",IF(L320>pLateDays,1,0)) | X320: =IF(Q320>=pHighCutoff,1,0) | Y320: =IF(M320="Returned",1,0)
A321: HC-100319 | B321: 45628 | C321: South | D321: Wholesale | E321: Lighting | F321: Pendant Light | G321: Consumer | H321: 22 | I321: 181.38 | J321: 0.2 | K321: 90.69 | L321: 3 | M321: Completed | N321: A. Shah | O321: No | P321: =H321*I321 | Q321: =P321*(1-J321) | R321: =H321*K321 | S321: =IF(Q321=0,"",(Q321-R321)/Q321) | T321: =YEAR(B321) | U321: =YEAR(B321)&"-Q"&ROUNDUP(MONTH(B321)/3,0) | V321: =TEXT(B321,"YYYY-MM") | W321: =IF(L321="","",IF(L321>pLateDays,1,0)) | X321: =IF(Q321>=pHighCutoff,1,0) | Y321: =IF(M321="Returned",1,0)
A322: HC-100320 | B322: 45507 | C322: East | D322: Online | E322: Textiles | F322: Linen Curtain | G322: Corporate | H322: 2 | I322: 86.26 | J322: 0.05 | K322: 38.82 | L322: 8 | M322: Completed | N322: K. Mensah | O322: No | P322: =H322*I322 | Q322: =P322*(1-J322) | R322: =H322*K322 | S322: =IF(Q322=0,"",(Q322-R322)/Q322) | T322: =YEAR(B322) | U322: =YEAR(B322)&"-Q"&ROUNDUP(MONTH(B322)/3,0) | V322: =TEXT(B322,"YYYY-MM") | W322: =IF(L322="","",IF(L322>pLateDays,1,0)) | X322: =IF(Q322>=pHighCutoff,1,0) | Y322: =IF(M322="Returned",1,0)
A323: HC-100321 | B323: 45508 | C323: South | D323: Store | E323: Textiles | F323: Wool Throw | G323: Consumer | H323: 3 | I323: 80.63 | J323: 0.01 | K323: 33.86 | L323: 4 | M323: Completed | N323: M. Okonkwo | O323: No | P323: =H323*I323 | Q323: =P323*(1-J323) | R323: =H323*K323 | S323: =IF(Q323=0,"",(Q323-R323)/Q323) | T323: =YEAR(B323) | U323: =YEAR(B323)&"-Q"&ROUNDUP(MONTH(B323)/3,0) | V323: =TEXT(B323,"YYYY-MM") | W323: =IF(L323="","",IF(L323>pLateDays,1,0)) | X323: =IF(Q323>=pHighCutoff,1,0) | Y323: =IF(M323="Returned",1,0)
A324: HC-100322 | B324: 45594 | C324: North | D324: Online | E324: Kitchen | F324: Ceramic Set | G324: Consumer | H324: 3 | I324: 92.75 | J324: 0.13 | K324: 35.25 | L324: 9 | M324: Completed | N324: J. Patel | O324: No | P324: =H324*I324 | Q324: =P324*(1-J324) | R324: =H324*K324 | S324: =IF(Q324=0,"",(Q324-R324)/Q324) | T324: =YEAR(B324) | U324: =YEAR(B324)&"-Q"&ROUNDUP(MONTH(B324)/3,0) | V324: =TEXT(B324,"YYYY-MM") | W324: =IF(L324="","",IF(L324>pLateDays,1,0)) | X324: =IF(Q324>=pHighCutoff,1,0) | Y324: =IF(M324="Returned",1,0)
A325: HC-100323 | B325: 45450 | C325: South | D325: Store | E325: Furniture | F325: Linen Sofa | G325: Consumer | H325: 1 | I325: 1167.04 | J325: 0.11 | K325: 770.25 | L325: 5 | M325: Completed | N325: L. Berger | O325: No | P325: =H325*I325 | Q325: =P325*(1-J325) | R325: =H325*K325 | S325: =IF(Q325=0,"",(Q325-R325)/Q325) | T325: =YEAR(B325) | U325: =YEAR(B325)&"-Q"&ROUNDUP(MONTH(B325)/3,0) | V325: =TEXT(B325,"YYYY-MM") | W325: =IF(L325="","",IF(L325>pLateDays,1,0)) | X325: =IF(Q325>=pHighCutoff,1,0) | Y325: =IF(M325="Returned",1,0)
... A349: HC-100347 | B349: 45421 | C349: West | D349: Wholesale | E349: Kitchen | F349: Chef Knife | G349: Consumer | H349: 16 | I349: 64.37 | J349: 0.29 | K349: 23.17 | L349: 4 | M349: Completed | N349: A. Shah | O349: No | P349: =H349*I349 | Q349: =P349*(1-J349) | R349: =H349*K349 | S349: =IF(Q349=0,"",(Q349-R349)/Q349) | T349: =YEAR(B349) | U349: =YEAR(B349)&"-Q"&ROUNDUP(MONTH(B349)/3,0) | V349: =TEXT(B349,"YYYY-MM") | W349: =IF(L349="","",IF(L349>pLateDays,1,0)) | X349: =IF(Q349>=pHighCutoff,1,0) | Y349: =IF(M349="Returned",1,0)
A350: HC-100348 | B350: 45629 | C350: North | D350: Store | E350: Furniture | F350: Lounge Chair | G350: Home Office | H350: 3 | I350: 458.2 | J350: 0 | K350: 274.92 | M350: Completed | N350: R. Ibarra | O350: No | P350: =H350*I350 | Q350: =P350*(1-J350) | R350: =H350*K350 | S350: =IF(Q350=0,"",(Q350-R350)/Q350) | T350: =YEAR(B350) | U350: =YEAR(B350)&"-Q"&ROUNDUP(MONTH(B350)/3,0) | V350: =TEXT(B350,"YYYY-MM") | W350: =IF(L350="","",IF(L350>pLateDays,1,0)) | X350: =IF(Q350>=pHighCutoff,1,0) | Y350: =IF(M350="Returned",1,0)
A351: HC-100349 | B351: 45639 | C351: East | D351: Store | E351: Textiles | F351: Wool Throw | G351: Consumer | H351: 4 | I351: 68.53 | J351: 0.01 | K351: 28.78 | L351: 11 | M351: Completed | N351: A. Shah | O351: No | P351: =H351*I351 | Q351: =P351*(1-J351) | R351: =H351*K351 | S351: =IF(Q351=0,"",(Q351-R351)/Q351) | T351: =YEAR(B351) | U351: =YEAR(B351)&"-Q"&ROUNDUP(MONTH(B351)/3,0) | V351: =TEXT(B351,"YYYY-MM") | W351: =IF(L351="","",IF(L351>pLateDays,1,0)) | X351: =IF(Q351>=pHighCutoff,1,0) | Y351: =IF(M351="Returned",1,0)
...

Sheet Chart_Data
A1: Chart source — every number is a formula against CleanData and the dashboard parameters.
A3: Region | B3: NetRevenue | C3: Orders | D3: AvgMargin | E3: TotalCost
A4: North | B4: =SUMIFS(CleanData[NetRevenue],CleanData[OrderDate],">="&pStart,CleanData[OrderDate],"<="&pEnd,CleanData[Channel],IF(pChannel="All","<>",pChannel),CleanData[Category],IF(pCategory="All","<>",pCategory),CleanData[Status],IF(pIncludeCancelled="Yes","<>","<>Cancelled"),CleanData[Region],A4) | C4: =COUNTIFS(CleanData[OrderDate],">="&pStart,CleanData[OrderDate],"<="&pEnd,CleanData[Channel],IF(pChannel="All","<>",pChannel),CleanData[Category],IF(pCategory="All","<>",pCategory),CleanData[Status],IF(pIncludeCancelled="Yes","<>","<>Cancelled"),CleanData[Region],A4) | D4: =IFERROR(AVERAGEIFS(CleanData[Margin],CleanData[OrderDate],">="&pStart,CleanData[OrderDate],"<="&pEnd,CleanData[Channel],IF(pChannel="All","<>",pChannel),CleanData[Category],IF(pCategory="All","<>",pCategory),CleanData[Status],IF(pIncludeCancelled="Yes","<>","<>Cancelled"),CleanData[Region],A4),NA()) | E4: =SUMIFS(CleanData[TotalCost],CleanData[OrderDate],">="&pStart,CleanData[OrderDate],"<="&pEnd,CleanData[Channel],IF(pChannel="All","<>",pChannel),CleanData[Category],IF(pCategory="All","<>",pCategory),CleanData[Status],IF(pIncludeCancelled="Yes","<>","<>Cancelled"),CleanData[Region],A4)
A5: South | B5: =SUMIFS(CleanData[NetRevenue],CleanData[OrderDate],">="&pStart,CleanData[OrderDate],"<="&pEnd,CleanData[Channel],IF(pChannel="All","<>",pChannel),CleanData[Category],IF(pCategory="All","<>",pCategory),CleanData[Status],IF(pIncludeCancelled="Yes","<>","<>Cancelled"),CleanData[Region],A5) | C5: =COUNTIFS(CleanData[OrderDate],">="&pStart,CleanData[OrderDate],"<="&pEnd,CleanData[Channel],IF(pChannel="All","<>",pChannel),CleanData[Category],IF(pCategory="All","<>",pCategory),CleanData[Status],IF(pIncludeCancelled="Yes","<>","<>Cancelled"),CleanData[Region],A5) | D5: =IFERROR(AVERAGEIFS(CleanData[Margin],CleanData[OrderDate],">="&pStart,CleanData[OrderDate],"<="&pEnd,CleanData[Channel],IF(pChannel="All","<>",pChannel),CleanData[Category],IF(pCategory="All","<>",pCategory),CleanData[Status],IF(pIncludeCancelled="Yes","<>","<>Cancelled"),CleanData[Region],A5),NA()) | E5: =SUMIFS(CleanData[TotalCost],CleanData[OrderDate],">="&pStart,CleanData[OrderDate],"<="&pEnd,CleanData[Channel],IF(pChannel="All","<>",pChannel),CleanData[Category],IF(pCategory="All","<>",pCategory),CleanData[Status],IF(pIncludeCancelled="Yes","<>","<>Cancelled"),CleanData[Region],A5)
A6: East | B6: =SUMIFS(CleanData[NetRevenue],CleanData[OrderDate],">="&pStart,CleanData[OrderDate],"<="&pEnd,CleanData[Channel],IF(pChannel="All","<>",pChannel),CleanData[Category],IF(pCategory="All","<>",pCategory),CleanData[Status],IF(pIncludeCancelled="Yes","<>","<>Cancelled"),CleanData[Region],A6) | C6: =COUNTIFS(CleanData[OrderDate],">="&pStart,CleanData[OrderDate],"<="&pEnd,CleanData[Channel],IF(pChannel="All","<>",pChannel),CleanData[Category],IF(pCategory="All","<>",pCategory),CleanData[Status],IF(pIncludeCancelled="Yes","<>","<>Cancelled"),CleanData[Region],A6) | D6: =IFERROR(AVERAGEIFS(CleanData[Margin],CleanData[OrderDate],">="&pStart,CleanData[OrderDate],"<="&pEnd,CleanData[Channel],IF(pChannel="All","<>",pChannel),CleanData[Category],IF(pCategory="All","<>",pCategory),CleanData[Status],IF(pIncludeCancelled="Yes","<>","<>Cancelled"),CleanData[Region],A6),NA()) | E6: =SUMIFS(CleanData[TotalCost],CleanData[OrderDate],">="&pStart,CleanData[OrderDate],"<="&pEnd,CleanData[Channel],IF(pChannel="All","<>",pChannel),CleanData[Category],IF(pCategory="All","<>",pCategory),CleanData[Status],IF(pIncludeCancelled="Yes","<>","<>Cancelled"),CleanData[Region],A6)
A7: West | B7: =SUMIFS(CleanData[NetRevenue],CleanData[OrderDate],">="&pStart,CleanData[OrderDate],"<="&pEnd,CleanData[Channel],IF(pChannel="All","<>",pChannel),CleanData[Category],IF(pCategory="All","<>",pCategory),CleanData[Status],IF(pIncludeCancelled="Yes","<>","<>Cancelled"),CleanData[Region],A7) | C7: =COUNTIFS(CleanData[OrderDate],">="&pStart,CleanData[OrderDate],"<="&pEnd,CleanData[Channel],IF(pChannel="All","<>",pChannel),CleanData[Category],IF(pCategory="All","<>",pCategory),CleanData[Status],IF(pIncludeCancelled="Yes","<>","<>Cancelled"),CleanData[Region],A7) | D7: =IFERROR(AVERAGEIFS(CleanData[Margin],CleanData[OrderDate],">="&pStart,CleanData[OrderDate],"<="&pEnd,CleanData[Channel],IF(pChannel="All","<>",pChannel),CleanData[Category],IF(pCategory="All","<>",pCategory),CleanData[Status],IF(pIncludeCancelled="Yes","<>","<>Cancelled"),CleanData[Region],A7),NA()) | E7: =SUMIFS(CleanData[TotalCost],CleanData[OrderDate],">="&pStart,CleanData[OrderDate],"<="&pEnd,CleanData[Channel],IF(pChannel="All","<>",pChannel),CleanData[Category],IF(pCategory="All","<>",pCategory),CleanData[Status],IF(pIncludeCancelled="Yes","<>","<>Cancelled"),CleanData[Region],A7)
A9: Channel | B9: Orders | C9: NetRevenue
A10: Store | B10: =COUNTIFS(CleanData[OrderDate],">="&pStart,CleanData[OrderDate],"<="&pEnd,CleanData[Region],IF(pRegion="All","<>",pRegion),CleanData[Category],IF(pCategory="All","<>",pCategory),CleanData[Status],IF(pIncludeCancelled="Yes","<>","<>Cancelled"),CleanData[Channel],A10) | C10: =SUMIFS(CleanData[NetRevenue],CleanData[OrderDate],">="&pStart,CleanData[OrderDate],"<="&pEnd,CleanData[Region],IF(pRegion="All","<>",pRegion),CleanData[Category],IF(pCategory="All","<>",pCategory),CleanData[Status],IF(pIncludeCancelled="Yes","<>","<>Cancelled"),CleanData[Channel],A10)
A11: Online | B11: =COUNTIFS(CleanData[OrderDate],">="&pStart,CleanData[OrderDate],"<="&pEnd,CleanData[Region],IF(pRegion="All","<>",pRegion),CleanData[Category],IF(pCategory="All","<>",pCategory),CleanData[Status],IF(pIncludeCancelled="Yes","<>","<>Cancelled"),CleanData[Channel],A11) | C11: =SUMIFS(CleanData[NetRevenue],CleanData[OrderDate],">="&pStart,CleanData[OrderDate],"<="&pEnd,CleanData[Region],IF(pRegion="All","<>",pRegion),CleanData[Category],IF(pCategory="All","<>",pCategory),CleanData[Status],IF(pIncludeCancelled="Yes","<>","<>Cancelled"),CleanData[Channel],A11)
A12: Wholesale | B12: =COUNTIFS(CleanData[OrderDate],">="&pStart,CleanData[OrderDate],"<="&pEnd,CleanData[Region],IF(pRegion="All","<>",pRegion),CleanData[Category],IF(pCategory="All","<>",pCategory),CleanData[Status],IF(pIncludeCancelled="Yes","<>","<>Cancelled"),CleanData[Channel],A12) | C12: =SUMIFS(CleanData[NetRevenue],CleanData[OrderDate],">="&pStart,CleanData[OrderDate],"<="&pEnd,CleanData[Region],IF(pRegion="All","<>",pRegion),CleanData[Category],IF(pCategory="All","<>",pCategory),CleanData[Status],IF(pIncludeCancelled="Yes","<>","<>Cancelled"),CleanData[Channel],A12)
A14: YearMonth | B14: NetRevenue | C14: Orders
A15: 2024-01 | B15: =SUMIFS(CleanData[NetRevenue],CleanData[OrderDate],">="&pStart,CleanData[OrderDate],"<="&pEnd,CleanData[Region],IF(pRegion="All","<>",pRegion),CleanData[Channel],IF(pChannel="All","<>",pChannel),CleanData[Category],IF(pCategory="All","<>",pCategory),CleanData[Status],IF(pIncludeCancelled="Yes","<>","<>Cancelled"),CleanData[YearMonth],A15) | C15: =COUNTIFS(CleanData[OrderDate],">="&pStart,CleanData[OrderDate],"<="&pEnd,CleanData[Region],IF(pRegion="All","<>",pRegion),CleanData[Channel],IF(pChannel="All","<>",pChannel),CleanData[Category],IF(pCategory="All","<>",pCategory),CleanData[Status],IF(pIncludeCancelled="Yes","<>","<>Cancelled"),CleanData[YearMonth],A15)
A16: 2024-02 | B16: =SUMIFS(CleanData[NetRevenue],CleanData[OrderDate],">="&pStart,CleanData[OrderDate],"<="&pEnd,CleanData[Region],IF(pRegion="All","<>",pRegion),CleanData[Channel],IF(pChannel="All","<>",pChannel),CleanData[Category],IF(pCategory="All","<>",pCategory),CleanData[Status],IF(pIncludeCancelled="Yes","<>","<>Cancelled"),CleanData[YearMonth],A16) | C16: =COUNTIFS(CleanData[OrderDate],">="&pStart,CleanData[OrderDate],"<="&pEnd,CleanData[Region],IF(pRegion="All","<>",pRegion),CleanData[Channel],IF(pChannel="All","<>",pChannel),CleanData[Category],IF(pCategory="All","<>",pCategory),CleanData[Status],IF(pIncludeCancelled="Yes","<>","<>Cancelled"),CleanData[YearMonth],A16)
A17: 2024-03 | B17: =SUMIFS(CleanData[NetRevenue],CleanData[OrderDate],">="&pStart,CleanData[OrderDate],"<="&pEnd,CleanData[Region],IF(pRegion="All","<>",pRegion),CleanData[Channel],IF(pChannel="All","<>",pChannel),CleanData[Category],IF(pCategory="All","<>",pCategory),CleanData[Status],IF(pIncludeCancelled="Yes","<>","<>Cancelled"),CleanData[YearMonth],A17) | C17: =COUNTIFS(CleanData[OrderDate],">="&pStart,CleanData[OrderDate],"<="&pEnd,CleanData[Region],IF(pRegion="All","<>",pRegion),CleanData[Channel],IF(pChannel="All","<>",pChannel),CleanData[Category],IF(pCategory="All","<>",pCategory),CleanData[Status],IF(pIncludeCancelled="Yes","<>","<>Cancelled"),CleanData[YearMonth],A17)
A18: 2024-04 | B18: =SUMIFS(CleanData[NetRevenue],CleanData[OrderDate],">="&pStart,CleanData[OrderDate],"<="&pEnd,CleanData[Region],IF(pRegion="All","<>",pRegion),CleanData[Channel],IF(pChannel="All","<>",pChannel),CleanData[Category],IF(pCategory="All","<>",pCategory),CleanData[Status],IF(pIncludeCancelled="Yes","<>","<>Cancelled"),CleanData[YearMonth],A18) | C18: =COUNTIFS(CleanData[OrderDate],">="&pStart,CleanData[OrderDate],"<="&pEnd,CleanData[Region],IF(pRegion="All","<>",pRegion),CleanData[Channel],IF(pChannel="All","<>",pChannel),CleanData[Category],IF(pCategory="All","<>",pCategory),CleanData[Status],IF(pIncludeCancelled="Yes","<>","<>Cancelled"),CleanData[YearMonth],A18)
A19: 2024-05 | B19: =SUMIFS(CleanData[NetRevenue],CleanData[OrderDate],">="&pStart,CleanData[OrderDate],"<="&pEnd,CleanData[Region],IF(pRegion="All","<>",pRegion),CleanData[Channel],IF(pChannel="All","<>",pChannel),CleanData[Category],IF(pCategory="All","<>",pCategory),CleanData[Status],IF(pIncludeCancelled="Yes","<>","<>Cancelled"),CleanData[YearMonth],A19) | C19: =COUNTIFS(CleanData[OrderDate],">="&pStart,CleanData[OrderDate],"<="&pEnd,CleanData[Region],IF(pRegion="All","<>",pRegion),CleanData[Channel],IF(pChannel="All","<>",pChannel),CleanData[Category],IF(pCategory="All","<>",pCategory),CleanData[Status],IF(pIncludeCancelled="Yes","<>","<>Cancelled"),CleanData[YearMonth],A19)
A20: 2024-06 | B20: =SUMIFS(CleanData[NetRevenue],CleanData[OrderDate],">="&pStart,CleanData[OrderDate],"<="&pEnd,CleanData[Region],IF(pRegion="All","<>",pRegion),CleanData[Channel],IF(pChannel="All","<>",pChannel),CleanData[Category],IF(pCategory="All","<>",pCategory),CleanData[Status],IF(pIncludeCancelled="Yes","<>","<>Cancelled"),CleanData[YearMonth],A20) | C20: =COUNTIFS(CleanData[OrderDate],">="&pStart,CleanData[OrderDate],"<="&pEnd,CleanData[Region],IF(pRegion="All","<>",pRegion),CleanData[Channel],IF(pChannel="All","<>",pChannel),CleanData[Category],IF(pCategory="All","<>",pCategory),CleanData[Status],IF(pIncludeCancelled="Yes","<>","<>Cancelled"),CleanData[YearMonth],A20)
A21: 2024-07 | B21: =SUMIFS(CleanData[NetRevenue],CleanData[OrderDate],">="&pStart,CleanData[OrderDate],"<="&pEnd,CleanData[Region],IF(pRegion="All","<>",pRegion),CleanData[Channel],IF(pChannel="All","<>",pChannel),CleanData[Category],IF(pCategory="All","<>",pCategory),CleanData[Status],IF(pIncludeCancelled="Yes","<>","<>Cancelled"),CleanData[YearMonth],A21) | C21: =COUNTIFS(CleanData[OrderDate],">="&pStart,CleanData[OrderDate],"<="&pEnd,CleanData[Region],IF(pRegion="All","<>",pRegion),CleanData[Channel],IF(pChannel="All","<>",pChannel),CleanData[Category],IF(pCategory="All","<>",pCategory),CleanData[Status],IF(pIncludeCancelled="Yes","<>","<>Cancelled"),CleanData[YearMonth],A21)
A22: 2024-08 | B22: =SUMIFS(CleanData[NetRevenue],CleanData[OrderDate],">="&pStart,CleanData[OrderDate],"<="&pEnd,CleanData[Region],IF(pRegion="All","<>",pRegion),CleanData[Channel],IF(pChannel="All","<>",pChannel),CleanData[Category],IF(pCategory="All","<>",pCategory),CleanData[Status],IF(pIncludeCancelled="Yes","<>","<>Cancelled"),CleanData[YearMonth],A22) | C22: =COUNTIFS(CleanData[OrderDate],">="&pStart,CleanData[OrderDate],"<="&pEnd,CleanData[Region],IF(pRegion="All","<>",pRegion),CleanData[Channel],IF(pChannel="All","<>",pChannel),CleanData[Category],IF(pCategory="All","<>",pCategory),CleanData[Status],IF(pIncludeCancelled="Yes","<>","<>Cancelled"),CleanData[YearMonth],A22)
A23: 2024-09 | B23: =SUMIFS(CleanData[NetRevenue],CleanData[OrderDate],">="&pStart,CleanData[OrderDate],"<="&pEnd,CleanData[Region],IF(pRegion="All","<>",pRegion),CleanData[Channel],IF(pChannel="All","<>",pChannel),CleanData[Category],IF(pCategory="All","<>",pCategory),CleanData[Status],IF(pIncludeCancelled="Yes","<>","<>Cancelled"),CleanData[YearMonth],A23) | C23: =COUNTIFS(CleanData[OrderDate],">="&pStart,CleanData[OrderDate],"<="&pEnd,CleanData[Region],IF(pRegion="All","<>",pRegion),CleanData[Channel],IF(pChannel="All","<>",pChannel),CleanData[Category],IF(pCategory="All","<>",pCategory),CleanData[Status],IF(pIncludeCancelled="Yes","<>","<>Cancelled"),CleanData[YearMonth],A23)
A24: 2024-10 | B24: =SUMIFS(CleanData[NetRevenue],CleanData[OrderDate],">="&pStart,CleanData[OrderDate],"<="&pEnd,CleanData[Region],IF(pRegion="All","<>",pRegion),CleanData[Channel],IF(pChannel="All","<>",pChannel),CleanData[Category],IF(pCategory="All","<>",pCategory),CleanData[Status],IF(pIncludeCancelled="Yes","<>","<>Cancelled"),CleanData[YearMonth],A24) | C24: =COUNTIFS(CleanData[OrderDate],">="&pStart,CleanData[OrderDate],"<="&pEnd,CleanData[Region],IF(pRegion="All","<>",pRegion),CleanData[Channel],IF(pChannel="All","<>",pChannel),CleanData[Category],IF(pCategory="All","<>",pCategory),CleanData[Status],IF(pIncludeCancelled="Yes","<>","<>Cancelled"),CleanData[YearMonth],A24)
A25: 2024-11 | B25: =SUMIFS(CleanData[NetRevenue],CleanData[OrderDate],">="&pStart,CleanData[OrderDate],"<="&pEnd,CleanData[Region],IF(pRegion="All","<>",pRegion),CleanData[Channel],IF(pChannel="All","<>",pChannel),CleanData[Category],IF(pCategory="All","<>",pCategory),CleanData[Status],IF(pIncludeCancelled="Yes","<>","<>Cancelled"),CleanData[YearMonth],A25) | C25: =COUNTIFS(CleanData[OrderDate],">="&pStart,CleanData[OrderDate],"<="&pEnd,CleanData[Region],IF(pRegion="All","<>",pRegion),CleanData[Channel],IF(pChannel="All","<>",pChannel),CleanData[Category],IF(pCategory="All","<>",pCategory),CleanData[Status],IF(pIncludeCancelled="Yes","<>","<>Cancelled"),CleanData[YearMonth],A25)
A26: 2024-12 | B26: =SUMIFS(CleanData[NetRevenue],CleanData[OrderDate],">="&pStart,CleanData[OrderDate],"<="&pEnd,CleanData[Region],IF(pRegion="All","<>",pRegion),CleanData[Channel],IF(pChannel="All","<>",pChannel),CleanData[Category],IF(pCategory="All","<>",pCategory),CleanData[Status],IF(pIncludeCancelled="Yes","<>","<>Cancelled"),CleanData[YearMonth],A26) | C26: =COUNTIFS(CleanData[OrderDate],">="&pStart,CleanData[OrderDate],"<="&pEnd,CleanData[Region],IF(pRegion="All","<>",pRegion),CleanData[Channel],IF(pChannel="All","<>",pChannel),CleanData[Category],IF(pCategory="All","<>",pCategory),CleanData[Status],IF(pIncludeCancelled="Yes","<>","<>Cancelled"),CleanData[YearMonth],A26)
... A35: 2025-09 | B35: =SUMIFS(CleanData[NetRevenue],CleanData[OrderDate],">="&pStart,CleanData[OrderDate],"<="&pEnd,CleanData[Region],IF(pRegion="All","<>",pRegion),CleanData[Channel],IF(pChannel="All","<>",pChannel),CleanData[Category],IF(pCategory="All","<>",pCategory),CleanData[Status],IF(pIncludeCancelled="Yes","<>","<>Cancelled"),CleanData[YearMonth],A35) | C35: =COUNTIFS(CleanData[OrderDate],">="&pStart,CleanData[OrderDate],"<="&pEnd,CleanData[Region],IF(pRegion="All","<>",pRegion),CleanData[Channel],IF(pChannel="All","<>",pChannel),CleanData[Category],IF(pCategory="All","<>",pCategory),CleanData[Status],IF(pIncludeCancelled="Yes","<>","<>Cancelled"),CleanData[YearMonth],A35)
A37: Category | B37: North | C37: South | D37: East | E37: West
A38: Furniture | B38: =SUMIFS(CleanData[NetRevenue],CleanData[OrderDate],">="&pStart,CleanData[OrderDate],"<="&pEnd,CleanData[Channel],IF(pChannel="All","<>",pChannel),CleanData[Status],IF(pIncludeCancelled="Yes","<>","<>Cancelled"),CleanData[Category],A38,CleanData[Region],B$37) | C38: =SUMIFS(CleanData[NetRevenue],CleanData[OrderDate],">="&pStart,CleanData[OrderDate],"<="&pEnd,CleanData[Channel],IF(pChannel="All","<>",pChannel),CleanData[Status],IF(pIncludeCancelled="Yes","<>","<>Cancelled"),CleanData[Category],A38,CleanData[Region],C$37) | D38: =SUMIFS(CleanData[NetRevenue],CleanData[OrderDate],">="&pStart,CleanData[OrderDate],"<="&pEnd,CleanData[Channel],IF(pChannel="All","<>",pChannel),CleanData[Status],IF(pIncludeCancelled="Yes","<>","<>Cancelled"),CleanData[Category],A38,CleanData[Region],D$37) | E38: =SUMIFS(CleanData[NetRevenue],CleanData[OrderDate],">="&pStart,CleanData[OrderDate],"<="&pEnd,CleanData[Channel],IF(pChannel="All","<>",pChannel),CleanData[Status],IF(pIncludeCancelled="Yes","<>","<>Cancelled"),CleanData[Category],A38,CleanData[Region],E$37)
A39: Lighting | B39: =SUMIFS(CleanData[NetRevenue],CleanData[OrderDate],">="&pStart,CleanData[OrderDate],"<="&pEnd,CleanData[Channel],IF(pChannel="All","<>",pChannel),CleanData[Status],IF(pIncludeCancelled="Yes","<>","<>Cancelled"),CleanData[Category],A39,CleanData[Region],B$37) | C39: =SUMIFS(CleanData[NetRevenue],CleanData[OrderDate],">="&pStart,CleanData[OrderDate],"<="&pEnd,CleanData[Channel],IF(pChannel="All","<>",pChannel),CleanData[Status],IF(pIncludeCancelled="Yes","<>","<>Cancelled"),CleanData[Category],A39,CleanData[Region],C$37) | D39: =SUMIFS(CleanData[NetRevenue],CleanData[OrderDate],">="&pStart,CleanData[OrderDate],"<="&pEnd,CleanData[Channel],IF(pChannel="All","<>",pChannel),CleanData[Status],IF(pIncludeCancelled="Yes","<>","<>Cancelled"),CleanData[Category],A39,CleanData[Region],D$37) | E39: =SUMIFS(CleanData[NetRevenue],CleanData[OrderDate],">="&pStart,CleanData[OrderDate],"<="&pEnd,CleanData[Channel],IF(pChannel="All","<>",pChannel),CleanData[Status],IF(pIncludeCancelled="Yes","<>","<>Cancelled"),CleanData[Category],A39,CleanData[Region],E$37)
A40: Textiles | B40: =SUMIFS(CleanData[NetRevenue],CleanData[OrderDate],">="&pStart,CleanData[OrderDate],"<="&pEnd,CleanData[Channel],IF(pChannel="All","<>",pChannel),CleanData[Status],IF(pIncludeCancelled="Yes","<>","<>Cancelled"),CleanData[Category],A40,CleanData[Region],B$37) | C40: =SUMIFS(CleanData[NetRevenue],CleanData[OrderDate],">="&pStart,CleanData[OrderDate],"<="&pEnd,CleanData[Channel],IF(pChannel="All","<>",pChannel),CleanData[Status],IF(pIncludeCancelled="Yes","<>","<>Cancelled"),CleanData[Category],A40,CleanData[Region],C$37) | D40: =SUMIFS(CleanData[NetRevenue],CleanData[OrderDate],">="&pStart,CleanData[OrderDate],"<="&pEnd,CleanData[Channel],IF(pChannel="All","<>",pChannel),CleanData[Status],IF(pIncludeCancelled="Yes","<>","<>Cancelled"),CleanData[Category],A40,CleanData[Region],D$37) | E40: =SUMIFS(CleanData[NetRevenue],CleanData[OrderDate],">="&pStart,CleanData[OrderDate],"<="&pEnd,CleanData[Channel],IF(pChannel="All","<>",pChannel),CleanData[Status],IF(pIncludeCancelled="Yes","<>","<>Cancelled"),CleanData[Category],A40,CleanData[Region],E$37)
A41: Kitchen | B41: =SUMIFS(CleanData[NetRevenue],CleanData[OrderDate],">="&pStart,CleanData[OrderDate],"<="&pEnd,CleanData[Channel],IF(pChannel="All","<>",pChannel),CleanData[Status],IF(pIncludeCancelled="Yes","<>","<>Cancelled"),CleanData[Category],A41,CleanData[Region],B$37) | C41: =SUMIFS(CleanData[NetRevenue],CleanData[OrderDate],">="&pStart,CleanData[OrderDate],"<="&pEnd,CleanData[Channel],IF(pChannel="All","<>",pChannel),CleanData[Status],IF(pIncludeCancelled="Yes","<>","<>Cancelled"),CleanData[Category],A41,CleanData[Region],C$37) | D41: =SUMIFS(CleanData[NetRevenue],CleanData[OrderDate],">="&pStart,CleanData[OrderDate],"<="&pEnd,CleanData[Channel],IF(pChannel="All","<>",pChannel),CleanData[Status],IF(pIncludeCancelled="Yes","<>","<>Cancelled"),CleanData[Category],A41,CleanData[Region],D$37) | E41: =SUMIFS(CleanData[NetRevenue],CleanData[OrderDate],">="&pStart,CleanData[OrderDate],"<="&pEnd,CleanData[Channel],IF(pChannel="All","<>",pChannel),CleanData[Status],IF(pIncludeCancelled="Yes","<>","<>Cancelled"),CleanData[Category],A41,CleanData[Region],E$37)
A43: Quarter | B43: NetRevenue
A44: 2024-Q1 | B44: =SUMIFS(CleanData[NetRevenue],CleanData[OrderDate],">="&pStart,CleanData[OrderDate],"<="&pEnd,CleanData[Region],IF(pRegion="All","<>",pRegion),CleanData[Channel],IF(pChannel="All","<>",pChannel),CleanData[Category],IF(pCategory="All","<>",pCategory),CleanData[Status],IF(pIncludeCancelled="Yes","<>","<>Cancelled"),CleanData[Quarter],A44)
A45: 2024-Q2 | B45: =SUMIFS(CleanData[NetRevenue],CleanData[OrderDate],">="&pStart,CleanData[OrderDate],"<="&pEnd,CleanData[Region],IF(pRegion="All","<>",pRegion),CleanData[Channel],IF(pChannel="All","<>",pChannel),CleanData[Category],IF(pCategory="All","<>",pCategory),CleanData[Status],IF(pIncludeCancelled="Yes","<>","<>Cancelled"),CleanData[Quarter],A45)
A46: 2024-Q3 | B46: =SUMIFS(CleanData[NetRevenue],CleanData[OrderDate],">="&pStart,CleanData[OrderDate],"<="&pEnd,CleanData[Region],IF(pRegion="All","<>",pRegion),CleanData[Channel],IF(pChannel="All","<>",pChannel),CleanData[Category],IF(pCategory="All","<>",pCategory),CleanData[Status],IF(pIncludeCancelled="Yes","<>","<>Cancelled"),CleanData[Quarter],A46)
A47: 2024-Q4 | B47: =SUMIFS(CleanData[NetRevenue],CleanData[OrderDate],">="&pStart,CleanData[OrderDate],"<="&pEnd,CleanData[Region],IF(pRegion="All","<>",pRegion),CleanData[Channel],IF(pChannel="All","<>",pChannel),CleanData[Category],IF(pCategory="All","<>",pCategory),CleanData[Status],IF(pIncludeCancelled="Yes","<>","<>Cancelled"),CleanData[Quarter],A47)
A48: 2025-Q1 | B48: =SUMIFS(CleanData[NetRevenue],CleanData[OrderDate],">="&pStart,CleanData[OrderDate],"<="&pEnd,CleanData[Region],IF(pRegion="All","<>",pRegion),CleanData[Channel],IF(pChannel="All","<>",pChannel),CleanData[Category],IF(pCategory="All","<>",pCategory),CleanData[Status],IF(pIncludeCancelled="Yes","<>","<>Cancelled"),CleanData[Quarter],A48)
A49: 2025-Q2 | B49: =SUMIFS(CleanData[NetRevenue],CleanData[OrderDate],">="&pStart,CleanData[OrderDate],"<="&pEnd,CleanData[Region],IF(pRegion="All","<>",pRegion),CleanData[Channel],IF(pChannel="All","<>",pChannel),CleanData[Category],IF(pCategory="All","<>",pCategory),CleanData[Status],IF(pIncludeCancelled="Yes","<>","<>Cancelled"),CleanData[Quarter],A49)
A50: 2025-Q3 | B50: =SUMIFS(CleanData[NetRevenue],CleanData[OrderDate],">="&pStart,CleanData[OrderDate],"<="&pEnd,CleanData[Region],IF(pRegion="All","<>",pRegion),CleanData[Channel],IF(pChannel="All","<>",pChannel),CleanData[Category],IF(pCategory="All","<>",pCategory),CleanData[Status],IF(pIncludeCancelled="Yes","<>","<>Cancelled"),CleanData[Quarter],A50)
A52: Status | B52: Orders
A53: Completed | B53: =COUNTIFS(CleanData[OrderDate],">="&pStart,CleanData[OrderDate],"<="&pEnd,CleanData[Region],IF(pRegion="All","<>",pRegion),CleanData[Channel],IF(pChannel="All","<>",pChannel),CleanData[Category],IF(pCategory="All","<>",pCategory),CleanData[Status],A53)
A54: Returned | B54: =COUNTIFS(CleanData[OrderDate],">="&pStart,CleanData[OrderDate],"<="&pEnd,CleanData[Region],IF(pRegion="All","<>",pRegion),CleanData[Channel],IF(pChannel="All","<>",pChannel),CleanData[Category],IF(pCategory="All","<>",pCategory),CleanData[Status],A54)
A55: Cancelled | B55: =COUNTIFS(CleanData[OrderDate],">="&pStart,CleanData[OrderDate],"<="&pEnd,CleanData[Region],IF(pRegion="All","<>",pRegion),CleanData[Channel],IF(pChannel="All","<>",pChannel),CleanData[Category],IF(pCategory="All","<>",pCategory),CleanData[Status],A55)
A57: Category | B57: ReturnRate | C57: Returned | D57: ReturnBase
A58: Furniture | B58: =IF(D58=0,NA(),C58/D58) | C58: =COUNTIFS(CleanData[OrderDate],">="&pStart,CleanData[OrderDate],"<="&pEnd,CleanData[Region],IF(pRegion="All","<>",pRegion),CleanData[Channel],IF(pChannel="All","<>",pChannel),CleanData[Category],A58,CleanData[Status],"Returned") | D58: =COUNTIFS(CleanData[OrderDate],">="&pStart,CleanData[OrderDate],"<="&pEnd,CleanData[Region],IF(pRegion="All","<>",pRegion),CleanData[Channel],IF(pChannel="All","<>",pChannel),CleanData[Category],A58,CleanData[Status],"<>Cancelled")
A59: Lighting | B59: =IF(D59=0,NA(),C59/D59) | C59: =COUNTIFS(CleanData[OrderDate],">="&pStart,CleanData[OrderDate],"<="&pEnd,CleanData[Region],IF(pRegion="All","<>",pRegion),CleanData[Channel],IF(pChannel="All","<>",pChannel),CleanData[Category],A59,CleanData[Status],"Returned") | D59: =COUNTIFS(CleanData[OrderDate],">="&pStart,CleanData[OrderDate],"<="&pEnd,CleanData[Region],IF(pRegion="All","<>",pRegion),CleanData[Channel],IF(pChannel="All","<>",pChannel),CleanData[Category],A59,CleanData[Status],"<>Cancelled")
A60: Textiles | B60: =IF(D60=0,NA(),C60/D60) | C60: =COUNTIFS(CleanData[OrderDate],">="&pStart,CleanData[OrderDate],"<="&pEnd,CleanData[Region],IF(pRegion="All","<>",pRegion),CleanData[Channel],IF(pChannel="All","<>",pChannel),CleanData[Category],A60,CleanData[Status],"Returned") | D60: =COUNTIFS(CleanData[OrderDate],">="&pStart,CleanData[OrderDate],"<="&pEnd,CleanData[Region],IF(pRegion="All","<>",pRegion),CleanData[Channel],IF(pChannel="All","<>",pChannel),CleanData[Category],A60,CleanData[Status],"<>Cancelled")
A61: Kitchen | B61: =IF(D61=0,NA(),C61/D61) | C61: =COUNTIFS(CleanData[OrderDate],">="&pStart,CleanData[OrderDate],"<="&pEnd,CleanData[Region],IF(pRegion="All","<>",pRegion),CleanData[Channel],IF(pChannel="All","<>",pChannel),CleanData[Category],A61,CleanData[Status],"Returned") | D61: =COUNTIFS(CleanData[OrderDate],">="&pStart,CleanData[OrderDate],"<="&pEnd,CleanData[Region],IF(pRegion="All","<>",pRegion),CleanData[Channel],IF(pChannel="All","<>",pChannel),CleanData[Category],A61,CleanData[Status],"<>Cancelled")
A63: YearMonth | B63: North | C63: South | D63: East | E63: West
A64: 2024-01 | B64: =COUNTIFS(CleanData[OrderDate],">="&pStart,CleanData[OrderDate],"<="&pEnd,CleanData[Channel],IF(pChannel="All","<>",pChannel),CleanData[Category],IF(pCategory="All","<>",pCategory),CleanData[Status],IF(pIncludeCancelled="Yes","<>","<>Cancelled"),CleanData[YearMonth],$A64,CleanData[Region],B$63) | C64: =COUNTIFS(CleanData[OrderDate],">="&pStart,CleanData[OrderDate],"<="&pEnd,CleanData[Channel],IF(pChannel="All","<>",pChannel),CleanData[Category],IF(pCategory="All","<>",pCategory),CleanData[Status],IF(pIncludeCancelled="Yes","<>","<>Cancelled"),CleanData[YearMonth],$A64,CleanData[Region],C$63) | D64: =COUNTIFS(CleanData[OrderDate],">="&pStart,CleanData[OrderDate],"<="&pEnd,CleanData[Channel],IF(pChannel="All","<>",pChannel),CleanData[Category],IF(pCategory="All","<>",pCategory),CleanData[Status],IF(pIncludeCancelled="Yes","<>","<>Cancelled"),CleanData[YearMonth],$A64,CleanData[Region],D$63) | E64: =COUNTIFS(CleanData[OrderDate],">="&pStart,CleanData[OrderDate],"<="&pEnd,CleanData[Channel],IF(pChannel="All","<>",pChannel),CleanData[Category],IF(pCategory="All","<>",pCategory),CleanData[Status],IF(pIncludeCancelled="Yes","<>","<>Cancelled"),CleanData[YearMonth],$A64,CleanData[Region],E$63)
A65: 2024-02 | B65: =COUNTIFS(CleanData[OrderDate],">="&pStart,CleanData[OrderDate],"<="&pEnd,CleanData[Channel],IF(pChannel="All","<>",pChannel),CleanData[Category],IF(pCategory="All","<>",pCategory),CleanData[Status],IF(pIncludeCancelled="Yes","<>","<>Cancelled"),CleanData[YearMonth],$A65,CleanData[Region],B$63) | C65: =COUNTIFS(CleanData[OrderDate],">="&pStart,CleanData[OrderDate],"<="&pEnd,CleanData[Channel],IF(pChannel="All","<>",pChannel),CleanData[Category],IF(pCategory="All","<>",pCategory),CleanData[Status],IF(pIncludeCancelled="Yes","<>","<>Cancelled"),CleanData[YearMonth],$A65,CleanData[Region],C$63) | D65: =COUNTIFS(CleanData[OrderDate],">="&pStart,CleanData[OrderDate],"<="&pEnd,CleanData[Channel],IF(pChannel="All","<>",pChannel),CleanData[Category],IF(pCategory="All","<>",pCategory),CleanData[Status],IF(pIncludeCancelled="Yes","<>","<>Cancelled"),CleanData[YearMonth],$A65,CleanData[Region],D$63) | E65: =COUNTIFS(CleanData[OrderDate],">="&pStart,CleanData[OrderDate],"<="&pEnd,CleanData[Channel],IF(pChannel="All","<>",pChannel),CleanData[Category],IF(pCategory="All","<>",pCategory),CleanData[Status],IF(pIncludeCancelled="Yes","<>","<>Cancelled"),CleanData[YearMonth],$A65,CleanData[Region],E$63)
A66: 2024-03 | B66: =COUNTIFS(CleanData[OrderDate],">="&pStart,CleanData[OrderDate],"<="&pEnd,CleanData[Channel],IF(pChannel="All","<>",pChannel),CleanData[Category],IF(pCategory="All","<>",pCategory),CleanData[Status],IF(pIncludeCancelled="Yes","<>","<>Cancelled"),CleanData[YearMonth],$A66,CleanData[Region],B$63) | C66: =COUNTIFS(CleanData[OrderDate],">="&pStart,CleanData[OrderDate],"<="&pEnd,CleanData[Channel],IF(pChannel="All","<>",pChannel),CleanData[Category],IF(pCategory="All","<>",pCategory),CleanData[Status],IF(pIncludeCancelled="Yes","<>","<>Cancelled"),CleanData[YearMonth],$A66,CleanData[Region],C$63) | D66: =COUNTIFS(CleanData[OrderDate],">="&pStart,CleanData[OrderDate],"<="&pEnd,CleanData[Channel],IF(pChannel="All","<>",pChannel),CleanData[Category],IF(pCategory="All","<>",pCategory),CleanData[Status],IF(pIncludeCancelled="Yes","<>","<>Cancelled"),CleanData[YearMonth],$A66,CleanData[Region],D$63) | E66: =COUNTIFS(CleanData[OrderDate],">="&pStart,CleanData[OrderDate],"<="&pEnd,CleanData[Channel],IF(pChannel="All","<>",pChannel),CleanData[Category],IF(pCategory="All","<>",pCategory),CleanData[Status],IF(pIncludeCancelled="Yes","<>","<>Cancelled"),CleanData[YearMonth],$A66,CleanData[Region],E$63)
A67: 2024-04 | B67: =COUNTIFS(CleanData[OrderDate],">="&pStart,CleanData[OrderDate],"<="&pEnd,CleanData[Channel],IF(pChannel="All","<>",pChannel),CleanData[Category],IF(pCategory="All","<>",pCategory),CleanData[Status],IF(pIncludeCancelled="Yes","<>","<>Cancelled"),CleanData[YearMonth],$A67,CleanData[Region],B$63) | C67: =COUNTIFS(CleanData[OrderDate],">="&pStart,CleanData[OrderDate],"<="&pEnd,CleanData[Channel],IF(pChannel="All","<>",pChannel),CleanData[Category],IF(pCategory="All","<>",pCategory),CleanData[Status],IF(pIncludeCancelled="Yes","<>","<>Cancelled"),CleanData[YearMonth],$A67,CleanData[Region],C$63) | D67: =COUNTIFS(CleanData[OrderDate],">="&pStart,CleanData[OrderDate],"<="&pEnd,CleanData[Channel],IF(pChannel="All","<>",pChannel),CleanData[Category],IF(pCategory="All","<>",pCategory),CleanData[Status],IF(pIncludeCancelled="Yes","<>","<>Cancelled"),CleanData[YearMonth],$A67,CleanData[Region],D$63) | E67: =COUNTIFS(CleanData[OrderDate],">="&pStart,CleanData[OrderDate],"<="&pEnd,CleanData[Channel],IF(pChannel="All","<>",pChannel),CleanData[Category],IF(pCategory="All","<>",pCategory),CleanData[Status],IF(pIncludeCancelled="Yes","<>","<>Cancelled"),CleanData[YearMonth],$A67,CleanData[Region],E$63)
A68: 2024-05 | B68: =COUNTIFS(CleanData[OrderDate],">="&pStart,CleanData[OrderDate],"<="&pEnd,CleanData[Channel],IF(pChannel="All","<>",pChannel),CleanData[Category],IF(pCategory="All","<>",pCategory),CleanData[Status],IF(pIncludeCancelled="Yes","<>","<>Cancelled"),CleanData[YearMonth],$A68,CleanData[Region],B$63) | C68: =COUNTIFS(CleanData[OrderDate],">="&pStart,CleanData[OrderDate],"<="&pEnd,CleanData[Channel],IF(pChannel="All","<>",pChannel),CleanData[Category],IF(pCategory="All","<>",pCategory),CleanData[Status],IF(pIncludeCancelled="Yes","<>","<>Cancelled"),CleanData[YearMonth],$A68,CleanData[Region],C$63) | D68: =COUNTIFS(CleanData[OrderDate],">="&pStart,CleanData[OrderDate],"<="&pEnd,CleanData[Channel],IF(pChannel="All","<>",pChannel),CleanData[Category],IF(pCategory="All","<>",pCategory),CleanData[Status],IF(pIncludeCancelled="Yes","<>","<>Cancelled"),CleanData[YearMonth],$A68,CleanData[Region],D$63) | E68: =COUNTIFS(CleanData[OrderDate],">="&pStart,CleanData[OrderDate],"<="&pEnd,CleanData[Channel],IF(pChannel="All","<>",pChannel),CleanData[Category],IF(pCategory="All","<>",pCategory),CleanData[Status],IF(pIncludeCancelled="Yes","<>","<>Cancelled"),CleanData[YearMonth],$A68,CleanData[Region],E$63)
A69: 2024-06 | B69: =COUNTIFS(CleanData[OrderDate],">="&pStart,CleanData[OrderDate],"<="&pEnd,CleanData[Channel],IF(pChannel="All","<>",pChannel),CleanData[Category],IF(pCategory="All","<>",pCategory),CleanData[Status],IF(pIncludeCancelled="Yes","<>","<>Cancelled"),CleanData[YearMonth],$A69,CleanData[Region],B$63) | C69: =COUNTIFS(CleanData[OrderDate],">="&pStart,CleanData[OrderDate],"<="&pEnd,CleanData[Channel],IF(pChannel="All","<>",pChannel),CleanData[Category],IF(pCategory="All","<>",pCategory),CleanData[Status],IF(pIncludeCancelled="Yes","<>","<>Cancelled"),CleanData[YearMonth],$A69,CleanData[Region],C$63) | D69: =COUNTIFS(CleanData[OrderDate],">="&pStart,CleanData[OrderDate],"<="&pEnd,CleanData[Channel],IF(pChannel="All","<>",pChannel),CleanData[Category],IF(pCategory="All","<>",pCategory),CleanData[Status],IF(pIncludeCancelled="Yes","<>","<>Cancelled"),CleanData[YearMonth],$A69,CleanData[Region],D$63) | E69: =COUNTIFS(CleanData[OrderDate],">="&pStart,CleanData[OrderDate],"<="&pEnd,CleanData[Channel],IF(pChannel="All","<>",pChannel),CleanData[Category],IF(pCategory="All","<>",pCategory),CleanData[Status],IF(pIncludeCancelled="Yes","<>","<>Cancelled"),CleanData[YearMonth],$A69,CleanData[Region],E$63)
A70: 2024-07 | B70: =COUNTIFS(CleanData[OrderDate],">="&pStart,CleanData[OrderDate],"<="&pEnd,CleanData[Channel],IF(pChannel="All","<>",pChannel),CleanData[Category],IF(pCategory="All","<>",pCategory),CleanData[Status],IF(pIncludeCancelled="Yes","<>","<>Cancelled"),CleanData[YearMonth],$A70,CleanData[Region],B$63) | C70: =COUNTIFS(CleanData[OrderDate],">="&pStart,CleanData[OrderDate],"<="&pEnd,CleanData[Channel],IF(pChannel="All","<>",pChannel),CleanData[Category],IF(pCategory="All","<>",pCategory),CleanData[Status],IF(pIncludeCancelled="Yes","<>","<>Cancelled"),CleanData[YearMonth],$A70,CleanData[Region],C$63) | D70: =COUNTIFS(CleanData[OrderDate],">="&pStart,CleanData[OrderDate],"<="&pEnd,CleanData[Channel],IF(pChannel="All","<>",pChannel),CleanData[Category],IF(pCategory="All","<>",pCategory),CleanData[Status],IF(pIncludeCancelled="Yes","<>","<>Cancelled"),CleanData[YearMonth],$A70,CleanData[Region],D$63) | E70: =COUNTIFS(CleanData[OrderDate],">="&pStart,CleanData[OrderDate],"<="&pEnd,CleanData[Channel],IF(pChannel="All","<>",pChannel),CleanData[Category],IF(pCategory="All","<>",pCategory),CleanData[Status],IF(pIncludeCancelled="Yes","<>","<>Cancelled"),CleanData[YearMonth],$A70,CleanData[Region],E$63)
A71: 2024-08 | B71: =COUNTIFS(CleanData[OrderDate],">="&pStart,CleanData[OrderDate],"<="&pEnd,CleanData[Channel],IF(pChannel="All","<>",pChannel),CleanData[Category],IF(pCategory="All","<>",pCategory),CleanData[Status],IF(pIncludeCancelled="Yes","<>","<>Cancelled"),CleanData[YearMonth],$A71,CleanData[Region],B$63) | C71: =COUNTIFS(CleanData[OrderDate],">="&pStart,CleanData[OrderDate],"<="&pEnd,CleanData[Channel],IF(pChannel="All","<>",pChannel),CleanData[Category],IF(pCategory="All","<>",pCategory),CleanData[Status],IF(pIncludeCancelled="Yes","<>","<>Cancelled"),CleanData[YearMonth],$A71,CleanData[Region],C$63) | D71: =COUNTIFS(CleanData[OrderDate],">="&pStart,CleanData[OrderDate],"<="&pEnd,CleanData[Channel],IF(pChannel="All","<>",pChannel),CleanData[Category],IF(pCategory="All","<>",pCategory),CleanData[Status],IF(pIncludeCancelled="Yes","<>","<>Cancelled"),CleanData[YearMonth],$A71,CleanData[Region],D$63) | E71: =COUNTIFS(CleanData[OrderDate],">="&pStart,CleanData[OrderDate],"<="&pEnd,CleanData[Channel],IF(pChannel="All","<>",pChannel),CleanData[Category],IF(pCategory="All","<>",pCategory),CleanData[Status],IF(pIncludeCancelled="Yes","<>","<>Cancelled"),CleanData[YearMonth],$A71,CleanData[Region],E$63)
A72: 2024-09 | B72: =COUNTIFS(CleanData[OrderDate],">="&pStart,CleanData[OrderDate],"<="&pEnd,CleanData[Channel],IF(pChannel="All","<>",pChannel),CleanData[Category],IF(pCategory="All","<>",pCategory),CleanData[Status],IF(pIncludeCancelled="Yes","<>","<>Cancelled"),CleanData[YearMonth],$A72,CleanData[Region],B$63) | C72: =COUNTIFS(CleanData[OrderDate],">="&pStart,CleanData[OrderDate],"<="&pEnd,CleanData[Channel],IF(pChannel="All","<>",pChannel),CleanData[Category],IF(pCategory="All","<>",pCategory),CleanData[Status],IF(pIncludeCancelled="Yes","<>","<>Cancelled"),CleanData[YearMonth],$A72,CleanData[Region],C$63) | D72: =COUNTIFS(CleanData[OrderDate],">="&pStart,CleanData[OrderDate],"<="&pEnd,CleanData[Channel],IF(pChannel="All","<>",pChannel),CleanData[Category],IF(pCategory="All","<>",pCategory),CleanData[Status],IF(pIncludeCancelled="Yes","<>","<>Cancelled"),CleanData[YearMonth],$A72,CleanData[Region],D$63) | E72: =COUNTIFS(CleanData[OrderDate],">="&pStart,CleanData[OrderDate],"<="&pEnd,CleanData[Channel],IF(pChannel="All","<>",pChannel),CleanData[Category],IF(pCategory="All","<>",pCategory),CleanData[Status],IF(pIncludeCancelled="Yes","<>","<>Cancelled"),CleanData[YearMonth],$A72,CleanData[Region],E$63)
A73: 2024-10 | B73: =COUNTIFS(CleanData[OrderDate],">="&pStart,CleanData[OrderDate],"<="&pEnd,CleanData[Channel],IF(pChannel="All","<>",pChannel),CleanData[Category],IF(pCategory="All","<>",pCategory),CleanData[Status],IF(pIncludeCancelled="Yes","<>","<>Cancelled"),CleanData[YearMonth],$A73,CleanData[Region],B$63) | C73: =COUNTIFS(CleanData[OrderDate],">="&pStart,CleanData[OrderDate],"<="&pEnd,CleanData[Channel],IF(pChannel="All","<>",pChannel),CleanData[Category],IF(pCategory="All","<>",pCategory),CleanData[Status],IF(pIncludeCancelled="Yes","<>","<>Cancelled"),CleanData[YearMonth],$A73,CleanData[Region],C$63) | D73: =COUNTIFS(CleanData[OrderDate],">="&pStart,CleanData[OrderDate],"<="&pEnd,CleanData[Channel],IF(pChannel="All","<>",pChannel),CleanData[Category],IF(pCategory="All","<>",pCategory),CleanData[Status],IF(pIncludeCancelled="Yes","<>","<>Cancelled"),CleanData[YearMonth],$A73,CleanData[Region],D$63) | E73: =COUNTIFS(CleanData[OrderDate],">="&pStart,CleanData[OrderDate],"<="&pEnd,CleanData[Channel],IF(pChannel="All","<>",pChannel),CleanData[Category],IF(pCategory="All","<>",pCategory),CleanData[Status],IF(pIncludeCancelled="Yes","<>","<>Cancelled"),CleanData[YearMonth],$A73,CleanData[Region],E$63)
A74: 2024-11 | B74: =COUNTIFS(CleanData[OrderDate],">="&pStart,CleanData[OrderDate],"<="&pEnd,CleanData[Channel],IF(pChannel="All","<>",pChannel),CleanData[Category],IF(pCategory="All","<>",pCategory),CleanData[Status],IF(pIncludeCancelled="Yes","<>","<>Cancelled"),CleanData[YearMonth],$A74,CleanData[Region],B$63) | C74: =COUNTIFS(CleanData[OrderDate],">="&pStart,CleanData[OrderDate],"<="&pEnd,CleanData[Channel],IF(pChannel="All","<>",pChannel),CleanData[Category],IF(pCategory="All","<>",pCategory),CleanData[Status],IF(pIncludeCancelled="Yes","<>","<>Cancelled"),CleanData[YearMonth],$A74,CleanData[Region],C$63) | D74: =COUNTIFS(CleanData[OrderDate],">="&pStart,CleanData[OrderDate],"<="&pEnd,CleanData[Channel],IF(pChannel="All","<>",pChannel),CleanData[Category],IF(pCategory="All","<>",pCategory),CleanData[Status],IF(pIncludeCancelled="Yes","<>","<>Cancelled"),CleanData[YearMonth],$A74,CleanData[Region],D$63) | E74: =COUNTIFS(CleanData[OrderDate],">="&pStart,CleanData[OrderDate],"<="&pEnd,CleanData[Channel],IF(pChannel="All","<>",pChannel),CleanData[Category],IF(pCategory="All","<>",pCategory),CleanData[Status],IF(pIncludeCancelled="Yes","<>","<>Cancelled"),CleanData[YearMonth],$A74,CleanData[Region],E$63)
A75: 2024-12 | B75: =COUNTIFS(CleanData[OrderDate],">="&pStart,CleanData[OrderDate],"<="&pEnd,CleanData[Channel],IF(pChannel="All","<>",pChannel),CleanData[Category],IF(pCategory="All","<>",pCategory),CleanData[Status],IF(pIncludeCancelled="Yes","<>","<>Cancelled"),CleanData[YearMonth],$A75,CleanData[Region],B$63) | C75: =COUNTIFS(CleanData[OrderDate],">="&pStart,CleanData[OrderDate],"<="&pEnd,CleanData[Channel],IF(pChannel="All","<>",pChannel),CleanData[Category],IF(pCategory="All","<>",pCategory),CleanData[Status],IF(pIncludeCancelled="Yes","<>","<>Cancelled"),CleanData[YearMonth],$A75,CleanData[Region],C$63) | D75: =COUNTIFS(CleanData[OrderDate],">="&pStart,CleanData[OrderDate],"<="&pEnd,CleanData[Channel],IF(pChannel="All","<>",pChannel),CleanData[Category],IF(pCategory="All","<>",pCategory),CleanData[Status],IF(pIncludeCancelled="Yes","<>","<>Cancelled"),CleanData[YearMonth],$A75,CleanData[Region],D$63) | E75: =COUNTIFS(CleanData[OrderDate],">="&pStart,CleanData[OrderDate],"<="&pEnd,CleanData[Channel],IF(pChannel="All","<>",pChannel),CleanData[Category],IF(pCategory="All","<>",pCategory),CleanData[Status],IF(pIncludeCancelled="Yes","<>","<>Cancelled"),CleanData[YearMonth],$A75,CleanData[Region],E$63)
... A84: 2025-09 | B84: =COUNTIFS(CleanData[OrderDate],">="&pStart,CleanData[OrderDate],"<="&pEnd,CleanData[Channel],IF(pChannel="All","<>",pChannel),CleanData[Category],IF(pCategory="All","<>",pCategory),CleanData[Status],IF(pIncludeCancelled="Yes","<>","<>Cancelled"),CleanData[YearMonth],$A84,CleanData[Region],B$63) | C84: =COUNTIFS(CleanData[OrderDate],">="&pStart,CleanData[OrderDate],"<="&pEnd,CleanData[Channel],IF(pChannel="All","<>",pChannel),CleanData[Category],IF(pCategory="All","<>",pCategory),CleanData[Status],IF(pIncludeCancelled="Yes","<>","<>Cancelled"),CleanData[YearMonth],$A84,CleanData[Region],C$63) | D84: =COUNTIFS(CleanData[OrderDate],">="&pStart,CleanData[OrderDate],"<="&pEnd,CleanData[Channel],IF(pChannel="All","<>",pChannel),CleanData[Category],IF(pCategory="All","<>",pCategory),CleanData[Status],IF(pIncludeCancelled="Yes","<>","<>Cancelled"),CleanData[YearMonth],$A84,CleanData[Region],D$63) | E84: =COUNTIFS(CleanData[OrderDate],">="&pStart,CleanData[OrderDate],"<="&pEnd,CleanData[Channel],IF(pChannel="All","<>",pChannel),CleanData[Category],IF(pCategory="All","<>",pCategory),CleanData[Status],IF(pIncludeCancelled="Yes","<>","<>Cancelled"),CleanData[YearMonth],$A84,CleanData[Region],E$63)
A86: Region | B86: Store | C86: Online | D86: Wholesale
A87: North | B87: =IF((COUNTIFS(CleanData[OrderDate],">="&pStart,CleanData[OrderDate],"<="&pEnd,CleanData[Category],IF(pCategory="All","<>",pCategory),CleanData[Status],IF(pIncludeCancelled="Yes","<>","<>Cancelled"),CleanData[Region],$A87,CleanData[Channel],B$86))=0,NA(),(SUMIFS(CleanData[NetRevenue],CleanData[OrderDate],">="&pStart,CleanData[OrderDate],"<="&pEnd,CleanData[Category],IF(pCategory="All","<>",pCategory),CleanData[Status],IF(pIncludeCancelled="Yes","<>","<>Cancelled"),CleanData[Region],$A87,CleanData[Channel],B$86))/(COUNTIFS(CleanData[OrderDate],">="&pStart,CleanData[OrderDate],"<="&pEnd,CleanData[Category],IF(pCategory="All","<>",pCategory),CleanData[Status],IF(pIncludeCancelled="Yes","<>","<>Cancelled"),CleanData[Region],$A87,CleanData[Channel],B$86))) | C87: =IF((COUNTIFS(CleanData[OrderDate],">="&pStart,CleanData[OrderDate],"<="&pEnd,CleanData[Category],IF(pCategory="All","<>",pCategory),CleanData[Status],IF(pIncludeCancelled="Yes","<>","<>Cancelled"),CleanData[Region],$A87,CleanData[Channel],C$86))=0,NA(),(SUMIFS(CleanData[NetRevenue],CleanData[OrderDate],">="&pStart,CleanData[OrderDate],"<="&pEnd,CleanData[Category],IF(pCategory="All","<>",pCategory),CleanData[Status],IF(pIncludeCancelled="Yes","<>","<>Cancelled"),CleanData[Region],$A87,CleanData[Channel],C$86))/(COUNTIFS(CleanData[OrderDate],">="&pStart,CleanData[OrderDate],"<="&pEnd,CleanData[Category],IF(pCategory="All","<>",pCategory),CleanData[Status],IF(pIncludeCancelled="Yes","<>","<>Cancelled"),CleanData[Region],$A87,CleanData[Channel],C$86))) | D87: =IF((COUNTIFS(CleanData[OrderDate],">="&pStart,CleanData[OrderDate],"<="&pEnd,CleanData[Category],IF(pCategory="All","<>",pCategory),CleanData[Status],IF(pIncludeCancelled="Yes","<>","<>Cancelled"),CleanData[Region],$A87,CleanData[Channel],D$86))=0,NA(),(SUMIFS(CleanData[NetRevenue],CleanData[OrderDate],">="&pStart,CleanData[OrderDate],"<="&pEnd,CleanData[Category],IF(pCategory="All","<>",pCategory),CleanData[Status],IF(pIncludeCancelled="Yes","<>","<>Cancelled"),CleanData[Region],$A87,CleanData[Channel],D$86))/(COUNTIFS(CleanData[OrderDate],">="&pStart,CleanData[OrderDate],"<="&pEnd,CleanData[Category],IF(pCategory="All","<>",pCategory),CleanData[Status],IF(pIncludeCancelled="Yes","<>","<>Cancelled"),CleanData[Region],$A87,CleanData[Channel],D$86)))
A88: South | B88: =IF((COUNTIFS(CleanData[OrderDate],">="&pStart,CleanData[OrderDate],"<="&pEnd,CleanData[Category],IF(pCategory="All","<>",pCategory),CleanData[Status],IF(pIncludeCancelled="Yes","<>","<>Cancelled"),CleanData[Region],$A88,CleanData[Channel],B$86))=0,NA(),(SUMIFS(CleanData[NetRevenue],CleanData[OrderDate],">="&pStart,CleanData[OrderDate],"<="&pEnd,CleanData[Category],IF(pCategory="All","<>",pCategory),CleanData[Status],IF(pIncludeCancelled="Yes","<>","<>Cancelled"),CleanData[Region],$A88,CleanData[Channel],B$86))/(COUNTIFS(CleanData[OrderDate],">="&pStart,CleanData[OrderDate],"<="&pEnd,CleanData[Category],IF(pCategory="All","<>",pCategory),CleanData[Status],IF(pIncludeCancelled="Yes","<>","<>Cancelled"),CleanData[Region],$A88,CleanData[Channel],B$86))) | C88: =IF((COUNTIFS(CleanData[OrderDate],">="&pStart,CleanData[OrderDate],"<="&pEnd,CleanData[Category],IF(pCategory="All","<>",pCategory),CleanData[Status],IF(pIncludeCancelled="Yes","<>","<>Cancelled"),CleanData[Region],$A88,CleanData[Channel],C$86))=0,NA(),(SUMIFS(CleanData[NetRevenue],CleanData[OrderDate],">="&pStart,CleanData[OrderDate],"<="&pEnd,CleanData[Category],IF(pCategory="All","<>",pCategory),CleanData[Status],IF(pIncludeCancelled="Yes","<>","<>Cancelled"),CleanData[Region],$A88,CleanData[Channel],C$86))/(COUNTIFS(CleanData[OrderDate],">="&pStart,CleanData[OrderDate],"<="&pEnd,CleanData[Category],IF(pCategory="All","<>",pCategory),CleanData[Status],IF(pIncludeCancelled="Yes","<>","<>Cancelled"),CleanData[Region],$A88,CleanData[Channel],C$86))) | D88: =IF((COUNTIFS(CleanData[OrderDate],">="&pStart,CleanData[OrderDate],"<="&pEnd,CleanData[Category],IF(pCategory="All","<>",pCategory),CleanData[Status],IF(pIncludeCancelled="Yes","<>","<>Cancelled"),CleanData[Region],$A88,CleanData[Channel],D$86))=0,NA(),(SUMIFS(CleanData[NetRevenue],CleanData[OrderDate],">="&pStart,CleanData[OrderDate],"<="&pEnd,CleanData[Category],IF(pCategory="All","<>",pCategory),CleanData[Status],IF(pIncludeCancelled="Yes","<>","<>Cancelled"),CleanData[Region],$A88,CleanData[Channel],D$86))/(COUNTIFS(CleanData[OrderDate],">="&pStart,CleanData[OrderDate],"<="&pEnd,CleanData[Category],IF(pCategory="All","<>",pCategory),CleanData[Status],IF(pIncludeCancelled="Yes","<>","<>Cancelled"),CleanData[Region],$A88,CleanData[Channel],D$86)))
A89: East | B89: =IF((COUNTIFS(CleanData[OrderDate],">="&pStart,CleanData[OrderDate],"<="&pEnd,CleanData[Category],IF(pCategory="All","<>",pCategory),CleanData[Status],IF(pIncludeCancelled="Yes","<>","<>Cancelled"),CleanData[Region],$A89,CleanData[Channel],B$86))=0,NA(),(SUMIFS(CleanData[NetRevenue],CleanData[OrderDate],">="&pStart,CleanData[OrderDate],"<="&pEnd,CleanData[Category],IF(pCategory="All","<>",pCategory),CleanData[Status],IF(pIncludeCancelled="Yes","<>","<>Cancelled"),CleanData[Region],$A89,CleanData[Channel],B$86))/(COUNTIFS(CleanData[OrderDate],">="&pStart,CleanData[OrderDate],"<="&pEnd,CleanData[Category],IF(pCategory="All","<>",pCategory),CleanData[Status],IF(pIncludeCancelled="Yes","<>","<>Cancelled"),CleanData[Region],$A89,CleanData[Channel],B$86))) | C89: =IF((COUNTIFS(CleanData[OrderDate],">="&pStart,CleanData[OrderDate],"<="&pEnd,CleanData[Category],IF(pCategory="All","<>",pCategory),CleanData[Status],IF(pIncludeCancelled="Yes","<>","<>Cancelled"),CleanData[Region],$A89,CleanData[Channel],C$86))=0,NA(),(SUMIFS(CleanData[NetRevenue],CleanData[OrderDate],">="&pStart,CleanData[OrderDate],"<="&pEnd,CleanData[Category],IF(pCategory="All","<>",pCategory),CleanData[Status],IF(pIncludeCancelled="Yes","<>","<>Cancelled"),CleanData[Region],$A89,CleanData[Channel],C$86))/(COUNTIFS(CleanData[OrderDate],">="&pStart,CleanData[OrderDate],"<="&pEnd,CleanData[Category],IF(pCategory="All","<>",pCategory),CleanData[Status],IF(pIncludeCancelled="Yes","<>","<>Cancelled"),CleanData[Region],$A89,CleanData[Channel],C$86))) | D89: =IF((COUNTIFS(CleanData[OrderDate],">="&pStart,CleanData[OrderDate],"<="&pEnd,CleanData[Category],IF(pCategory="All","<>",pCategory),CleanData[Status],IF(pIncludeCancelled="Yes","<>","<>Cancelled"),CleanData[Region],$A89,CleanData[Channel],D$86))=0,NA(),(SUMIFS(CleanData[NetRevenue],CleanData[OrderDate],">="&pStart,CleanData[OrderDate],"<="&pEnd,CleanData[Category],IF(pCategory="All","<>",pCategory),CleanData[Status],IF(pIncludeCancelled="Yes","<>","<>Cancelled"),CleanData[Region],$A89,CleanData[Channel],D$86))/(COUNTIFS(CleanData[OrderDate],">="&pStart,CleanData[OrderDate],"<="&pEnd,CleanData[Category],IF(pCategory="All","<>",pCategory),CleanData[Status],IF(pIncludeCancelled="Yes","<>","<>Cancelled"),CleanData[Region],$A89,CleanData[Channel],D$86)))
A90: West | B90: =IF((COUNTIFS(CleanData[OrderDate],">="&pStart,CleanData[OrderDate],"<="&pEnd,CleanData[Category],IF(pCategory="All","<>",pCategory),CleanData[Status],IF(pIncludeCancelled="Yes","<>","<>Cancelled"),CleanData[Region],$A90,CleanData[Channel],B$86))=0,NA(),(SUMIFS(CleanData[NetRevenue],CleanData[OrderDate],">="&pStart,CleanData[OrderDate],"<="&pEnd,CleanData[Category],IF(pCategory="All","<>",pCategory),CleanData[Status],IF(pIncludeCancelled="Yes","<>","<>Cancelled"),CleanData[Region],$A90,CleanData[Channel],B$86))/(COUNTIFS(CleanData[OrderDate],">="&pStart,CleanData[OrderDate],"<="&pEnd,CleanData[Category],IF(pCategory="All","<>",pCategory),CleanData[Status],IF(pIncludeCancelled="Yes","<>","<>Cancelled"),CleanData[Region],$A90,CleanData[Channel],B$86))) | C90: =IF((COUNTIFS(CleanData[OrderDate],">="&pStart,CleanData[OrderDate],"<="&pEnd,CleanData[Category],IF(pCategory="All","<>",pCategory),CleanData[Status],IF(pIncludeCancelled="Yes","<>","<>Cancelled"),CleanData[Region],$A90,CleanData[Channel],C$86))=0,NA(),(SUMIFS(CleanData[NetRevenue],CleanData[OrderDate],">="&pStart,CleanData[OrderDate],"<="&pEnd,CleanData[Category],IF(pCategory="All","<>",pCategory),CleanData[Status],IF(pIncludeCancelled="Yes","<>","<>Cancelled"),CleanData[Region],$A90,CleanData[Channel],C$86))/(COUNTIFS(CleanData[OrderDate],">="&pStart,CleanData[OrderDate],"<="&pEnd,CleanData[Category],IF(pCategory="All","<>",pCategory),CleanData[Status],IF(pIncludeCancelled="Yes","<>","<>Cancelled"),CleanData[Region],$A90,CleanData[Channel],C$86))) | D90: =IF((COUNTIFS(CleanData[OrderDate],">="&pStart,CleanData[OrderDate],"<="&pEnd,CleanData[Category],IF(pCategory="All","<>",pCategory),CleanData[Status],IF(pIncludeCancelled="Yes","<>","<>Cancelled"),CleanData[Region],$A90,CleanData[Channel],D$86))=0,NA(),(SUMIFS(CleanData[NetRevenue],CleanData[OrderDate],">="&pStart,CleanData[OrderDate],"<="&pEnd,CleanData[Category],IF(pCategory="All","<>",pCategory),CleanData[Status],IF(pIncludeCancelled="Yes","<>","<>Cancelled"),CleanData[Region],$A90,CleanData[Channel],D$86))/(COUNTIFS(CleanData[OrderDate],">="&pStart,CleanData[OrderDate],"<="&pEnd,CleanData[Category],IF(pCategory="All","<>",pCategory),CleanData[Status],IF(pIncludeCancelled="Yes","<>","<>Cancelled"),CleanData[Region],$A90,CleanData[Channel],D$86)))

Sheet Analysis
A1: Analysis
A2: Live SUMIFS summaries follow the dashboard filters. The top-10 list is a snapshot from the last pipeline run at All / All / All.
B5: =Chart_Data!A4 | C5: =Chart_Data!B4 | D5: =Chart_Data!C4 | E5: =IF(D5=0,NA(),C5/D5) | F5: =IF(C5=0,NA(),(C5-Chart_Data!E4)/C5) | G5: =Chart_Data!D4
B6: =Chart_Data!A5 | C6: =Chart_Data!B5 | D6: =Chart_Data!C5 | E6: =IF(D6=0,NA(),C6/D6) | F6: =IF(C6=0,NA(),(C6-Chart_Data!E5)/C6) | G6: =Chart_Data!D5
B7: =Chart_Data!A6 | C7: =Chart_Data!B6 | D7: =Chart_Data!C6 | E7: =IF(D7=0,NA(),C7/D7) | F7: =IF(C7=0,NA(),(C7-Chart_Data!E6)/C7) | G7: =Chart_Data!D6
B8: =Chart_Data!A7 | C8: =Chart_Data!B7 | D8: =Chart_Data!C7 | E8: =IF(D8=0,NA(),C8/D8) | F8: =IF(C8=0,NA(),(C8-Chart_Data!E7)/C8) | G8: =Chart_Data!D7
B11: Top 10 orders by net revenue (pipeline snapshot, default filters)
B13: HC-100483 | C13: 45785 | D13: West | E13: Furniture | F13: Linen Sofa | G13: Completed | H13: 29393.95 | I13: 0.19512416
B14: HC-100098 | C14: 45834 | D14: South | E14: Furniture | F14: Linen Sofa | G14: Completed | H14: 28854.411 | I14: 0.24138324
B15: HC-101367 | C15: 45656 | D15: East | E15: Furniture | F15: Linen Sofa | G15: Completed | H15: 27550.785 | I15: 0.1199964
B16: HC-101139 | C16: 45875 | D16: East | E16: Furniture | F16: Linen Sofa | G16: Completed | H16: 26399.976 | I16: 0.20481708
B17: HC-100766 | C17: 45835 | D17: West | E17: Furniture | F17: Linen Sofa | G17: Completed | H17: 25359.09 | I17: 0.20481846
B18: HC-101257 | C18: 45801 | D18: West | E18: Furniture | F18: Linen Sofa | G18: Completed | H18: 24770.535 | I18: 0.19511954
B19: HC-100479 | C19: 45849 | D19: West | E19: Furniture | F19: Linen Sofa | G19: Completed | H19: 23947.739 | I19: 0.1951282
B20: HC-100845 | C20: 45374 | D20: South | E20: Furniture | F20: Linen Sofa | G20: Completed | H20: 23405.242 | I20: 0.043480927
B21: HC-101568 | C21: 45703 | D21: North | E21: Furniture | F21: Linen Sofa | G21: Completed | H21: 23215.853 | I21: 0.029413212
B22: HC-100799 | C22: 45806 | D22: West | E22: Furniture | F22: Oak Desk | G22: Completed | H22: 23155.318 | I22: 0.27059519
B24: Weighted margin is (net revenue - cost) / net revenue. Unweighted margin is the average of order-level margins. A region can look healthier on one definition than the other when a few large wholesale tickets dominate.

Sheet Dashboard
A1: Harbor & Co. · Sales performance
A2: Excel pipeline dashboard. Change the controls, then let Excel calculate. Comparison charts ignore the filter that would collapse them.
C5: All | E5: All | G5: All | I5: No | K5: 45292 | M5: 45930
A6: Shipment lateness and the low-margin floor live on Parameters. The high-value cutoff is calculated for this saved window; rerun the pipeline after changing dates if you need a new percentile.
A8: Net revenue | C8: Orders | E8: Average order value | G8: Gross margin | I8: Return rate | K8: On-time fulfillment | M8: High-value orders | O8: Low-margin orders
A9: =SUMIFS(CleanData[NetRevenue],CleanData[OrderDate],">="&pStart,CleanData[OrderDate],"<="&pEnd,CleanData[Region],IF(pRegion="All","<>",pRegion),CleanData[Channel],IF(pChannel="All","<>",pChannel),CleanData[Category],IF(pCategory="All","<>",pCategory),CleanData[Status],IF(pIncludeCancelled="Yes","<>","<>Cancelled")) | C9: =COUNTIFS(CleanData[OrderDate],">="&pStart,CleanData[OrderDate],"<="&pEnd,CleanData[Region],IF(pRegion="All","<>",pRegion),CleanData[Channel],IF(pChannel="All","<>",pChannel),CleanData[Category],IF(pCategory="All","<>",pCategory),CleanData[Status],IF(pIncludeCancelled="Yes","<>","<>Cancelled")) | E9: =IF(C9=0,NA(),A9/C9) | G9: =IF(A9=0,NA(),(A9-SUMIFS(CleanData[TotalCost],CleanData[OrderDate],">="&pStart,CleanData[OrderDate],"<="&pEnd,CleanData[Region],IF(pRegion="All","<>",pRegion),CleanData[Channel],IF(pChannel="All","<>",pChannel),CleanData[Category],IF(pCategory="All","<>",pCategory),CleanData[Status],IF(pIncludeCancelled="Yes","<>","<>Cancelled")))/A9) | I9: =IF(COUNTIFS(CleanData[OrderDate],">="&pStart,CleanData[OrderDate],"<="&pEnd,CleanData[Region],IF(pRegion="All","<>",pRegion),CleanData[Channel],IF(pChannel="All","<>",pChannel),CleanData[Category],IF(pCategory="All","<>",pCategory),CleanData[Status],"<>Cancelled")=0,NA(),COUNTIFS(CleanData[OrderDate],">="&pStart,CleanData[OrderDate],"<="&pEnd,CleanData[Region],IF(pRegion="All","<>",pRegion),CleanData[Channel],IF(pChannel="All","<>",pChannel),CleanData[Category],IF(pCategory="All","<>",pCategory),CleanData[Status],"Returned")/COUNTIFS(CleanData[OrderDate],">="&pStart,CleanData[OrderDate],"<="&pEnd,CleanData[Region],IF(pRegion="All","<>",pRegion),CleanData[Channel],IF(pChannel="All","<>",pChannel),CleanData[Category],IF(pCategory="All","<>",pCategory),CleanData[Status],"<>Cancelled")) | K9: =IF(COUNTIFS(CleanData[OrderDate],">="&pStart,CleanData[OrderDate],"<="&pEnd,CleanData[Region],IF(pRegion="All","<>",pRegion),CleanData[Channel],IF(pChannel="All","<>",pChannel),CleanData[Category],IF(pCategory="All","<>",pCategory),CleanData[ShipDays],">="&0,CleanData[Status],"<>Cancelled")=0,NA(),COUNTIFS(CleanData[OrderDate],">="&pStart,CleanData[OrderDate],"<="&pEnd,CleanData[Region],IF(pRegion="All","<>",pRegion),CleanData[Channel],IF(pChannel="All","<>",pChannel),CleanData[Category],IF(pCategory="All","<>",pCategory),CleanData[LateFlag],0,CleanData[Status],"<>Cancelled")/COUNTIFS(CleanData[OrderDate],">="&pStart,CleanData[OrderDate],"<="&pEnd,CleanData[Region],IF(pRegion="All","<>",pRegion),CleanData[Channel],IF(pChannel="All","<>",pChannel),CleanData[Category],IF(pCategory="All","<>",pCategory),CleanData[ShipDays],">="&0,CleanData[Status],"<>Cancelled")) | M9: =COUNTIFS(CleanData[OrderDate],">="&pStart,CleanData[OrderDate],"<="&pEnd,CleanData[Region],IF(pRegion="All","<>",pRegion),CleanData[Channel],IF(pChannel="All","<>",pChannel),CleanData[Category],IF(pCategory="All","<>",pCategory),CleanData[Status],IF(pIncludeCancelled="Yes","<>","<>Cancelled"),CleanData[HighValueFlag],1) | O9: =COUNTIFS(CleanData[OrderDate],">="&pStart,CleanData[OrderDate],"<="&pEnd,CleanData[Region],IF(pRegion="All","<>",pRegion),CleanData[Channel],IF(pChannel="All","<>",pChannel),CleanData[Category],IF(pCategory="All","<>",pCategory),CleanData[Status],IF(pIncludeCancelled="Yes","<>","<>Cancelled"),CleanData[Margin],"<"&pLowMargin)

Sheet Insights
A1: Insights
A2: Written from the latest pipeline run at the default filters.
B4: # Key insights Harbor & Co. recorded $2,220,660 of in-scope net revenue across 1,558 orders from 2024-01-01 to 2025-09-30. Average order value was $1,425 and weighted gross margin was 29.4%. West is the largest region at $732,437 (487 orders). East is the smallest at $425,069. South leads weighted margin at 31.3%; East is lowest at 26.1%. Furniture contributes the most category revenue ($1,698,590). Textiles has the highest return rate at 13.5%. Overall return rate is 7.1% (111 returns out of 1,558 non-cancelled orders). Wholesale is the largest channel by net revenue ($1,286,845). The strongest month is 2024-11 at $220,964; the softest month inside the window is 2024-02 at $40,088. On-time fulfillment (shipped within 7 days, cancelled orders excluded) is 75.5%. 156 orders meet or exceed the 90% net-revenue cutoff of $3,065. 21 in-scope orders sit below the 15.0% margin floor. The largest single order is HC-100483 (West, Linen Sofa) at $29,394. The extract started with 1,649 rows and finished with 1,618 analysis-ready orders. Exact duplicate rows removed: 26. Order-ID conflicts resolved by keeping the higher net revenue: 1. Rows rejected for invalid region, date, quantity, or price: 4. Negative quantities corrected: 1. Blank segments imputed to Unknown: 77. Implausible ship days cleared: 1. ## Actions suggested by the numbers - Review fulfillment in the region with the weakest margin (East) before adding promotional discount. - Textiles returns are high enough to justify a quality or sizing check before the next peak season. - Hold cancelled orders out of sales KPIs (the workbook default). Turn the dashboard switch to Yes only when the question is about demand originally written, not demand kept. - Treat orders at or above $3,065 as a named follow-up list; there are 156 of them in the current window.

Sheet QA_Tests
A1: QA tests
A2: Status formulas compare Excel calculations with the values locked by the pipeline. Open in Excel and calculate.
B5: Raw rows | C5: 1649 | D5: =COUNTA(RawData[OrderID]) | E5: =IF(ABS(C5-D5)<0.05,"PASS","FAIL") | F5: Every source row, including duplicates and edge cases.
B6: Clean rows | C6: 1618 | D6: =COUNTA(CleanData[OrderID]) | E6: =IF(ABS(C6-D6)<0.05,"PASS","FAIL") | F6: One row per surviving OrderID.
B7: Rejected rows | C7: 31 | D7: =COUNTA(RejectedData[OrderID]) | E7: =IF(ABS(C7-D7)<0.05,"PASS","FAIL") | F7: Duplicates, invalid rows, and OrderID conflicts.
B8: Row balance | C8: 1649 | D8: =COUNTA(CleanData[OrderID])+COUNTA(RejectedData[OrderID]) | E8: =IF(ABS(C8-D8)<0.05,"PASS","FAIL") | F8: Raw count must equal clean plus rejected.
B9: Net revenue | C9: 2220659.8 | D9: =ROUND(SUMIFS(CleanData[NetRevenue],CleanData[OrderDate],">="&pStart,CleanData[OrderDate],"<="&pEnd,CleanData[Region],IF(pRegion="All","<>",pRegion),CleanData[Channel],IF(pChannel="All","<>",pChannel),CleanData[Category],IF(pCategory="All","<>",pCategory),CleanData[Status],IF(pIncludeCancelled="Yes","<>","<>Cancelled")),2) | E9: =IF(ABS(C9-D9)<0.05,"PASS","FAIL") | F9: Default filters, cancelled excluded.
B10: Orders | C10: 1558 | D10: =COUNTIFS(CleanData[OrderDate],">="&pStart,CleanData[OrderDate],"<="&pEnd,CleanData[Region],IF(pRegion="All","<>",pRegion),CleanData[Channel],IF(pChannel="All","<>",pChannel),CleanData[Category],IF(pCategory="All","<>",pCategory),CleanData[Status],IF(pIncludeCancelled="Yes","<>","<>Cancelled")) | E10: =IF(ABS(C10-D10)<0.05,"PASS","FAIL") | F10: Default filters, cancelled excluded.
B11: North net revenue | C11: 611412.62 | D11: =ROUND(Chart_Data!B4,2) | E11: =IF(ABS(C11-D11)<0.05,"PASS","FAIL") | F11: Region chart ignores the region dropdown and honors the other filters.
B12: High-value cutoff | C12: 3064.63 | D12: =ROUND(pHighCutoff,2) | E12: =IF(ABS(C12-D12)<0.05,"PASS","FAIL") | F12: Percentile cutoff stored at pipeline run time.
B13: High-value orders | C13: 156 | D13: =COUNTIFS(CleanData[OrderDate],">="&pStart,CleanData[OrderDate],"<="&pEnd,CleanData[Region],IF(pRegion="All","<>",pRegion),CleanData[Channel],IF(pChannel="All","<>",pChannel),CleanData[Category],IF(pCategory="All","<>",pCategory),CleanData[Status],IF(pIncludeCancelled="Yes","<>","<>Cancelled"),CleanData[HighValueFlag],1) | E13: =IF(ABS(C13-D13)<0.05,"PASS","FAIL") | F13: Uses the stored cutoff.
B14: Dashboard region default | C14: All | D14: =pRegion | E14: =IF(C14=D14,"PASS","FAIL") | F14: Named range points at the dashboard control.
B15: Include cancelled default | C15: No | D15: =pIncludeCancelled | E15: =IF(C15=D15,"PASS","FAIL") | F15: Sales KPIs exclude cancelled orders until this switch is Yes.

Sheet Rejected_Rows
A1: OrderID | B1: Reason | C1: Detail | D1: OrderDate | E1: Region | F1: Status | G1: SourceRow
A2: HC-100112 | B2: exact_duplicate | C2: exact_duplicate | D2: 11/15/2024 | E2: Sout | F2: Completed | G2: 1602
A3: HC-100049 | B3: exact_duplicate | C3: exact_duplicate | D3: 22-Aug-24 | E3: South | F3: Completed | G3: 1603
A4: HC-101167 | B4: exact_duplicate | C4: exact_duplicate | D4: 29.04.2025 | E4: south | F4: Canceled | G4: 1604
A5: HC-101111 | B5: exact_duplicate | C5: exact_duplicate | D5: 08.01.2025 | E5: East | F5: Completed | G5: 1605
A6: HC-101006 | B6: exact_duplicate | C6: exact_duplicate | D6: 2025/06/11 | E6: East | F6: Cancelled | G6: 1606
A7: HC-100294 | B7: exact_duplicate | C7: exact_duplicate | D7: 2024/05/29 | E7: North | F7: Completed | G7: 1607
A8: HC-101226 | B8: exact_duplicate | C8: exact_duplicate | D8: 2024/08/19 | E8: North | F8: Completed | G8: 1608
A9: HC-100099 | B9: exact_duplicate | C9: exact_duplicate | D9: 02.06.2024 | E9: South | F9: Completed | G9: 1609
A10: HC-101428 | B10: exact_duplicate | C10: exact_duplicate | D10: 05/06/2024 | E10: West | F10: Completed | G10: 1610
A11: HC-101016 | B11: exact_duplicate | C11: exact_duplicate | D11: 07/23/2024 | E11: South | F11: Cancelled | G11: 1611
A12: HC-100872 | B12: exact_duplicate | C12: exact_duplicate | D12: 08/22/2024 | E12: North | F12: Compleated | G12: 1612
A13: HC-100858 | B13: exact_duplicate | C13: exact_duplicate | D13: 2024/04/18 | E13: South | F13: Completed | G13: 1613
... A31: EDGE-PRICE | B31: bad_price | C31: bad_price | D31: 12/01/2024 | E31: North | F31: Completed | G31: 1645
A32: EDGE-CONF | B32: order_id_conflict | C32: A higher net-revenue row with the same OrderID was kept | D32: 2024-03-03 | E32: North | F32: Completed

Sheet Data_Dictionary
A1: Data dictionary
A2: Field definitions for the cleaned orders table.
B5: OrderID | C5: Order identifier | D5: Conflicts keep the higher net-revenue row.
B6: OrderDate | C6: Order date | D6: Parsed from mixed raw formats, then stored as a real date.
B7: Region | C7: Sales region | D7: North, South, East, West after alias cleanup.
B8: Channel | C8: Route to customer | D8: Store, Online, or Wholesale.
B9: Category | C9: Merchandise family | D9: Furniture, Lighting, Textiles, Kitchen.
B10: Product | C10: SKU name | D10: Free text from the catalog.
B11: Segment | C11: Customer segment | D11: Blank source values become Unknown.
B12: Quantity | C12: Units | D12: Negative quantities are flipped and flagged. Zero quantities are rejected.
B13: UnitPrice | C13: Selling price per unit | D13: Currency text and spelled numbers are parsed in the transform.
B14: Discount | C14: Discount fraction | D14: 20% and 0.20 both become 0.20. Values between 1 and 100 are treated as percents.
B15: UnitCost | C15: Cost per unit | D15: Must be zero or positive.
B16: ShipDays | C16: Days from order to ship | D16: Blank, N/A, negative, or above 120 days are cleared and excluded from on-time rate.
... B24: ReturnFlag | C24: 1 when status is Returned | D24: Used for audit, not for the return-rate denominator.

Sheet Cleaning_Log
A1: Cleaning log
A2: Counts from the transform that produced this workbook.
B4: Metric | C4: Value
B5: Raw rows | C5: 1649
B6: Clean rows | C6: 1618
B7: Rejected rows | C7: 31
B8: Exact duplicates | C8: 26
B9: Row balance holds | C9: Yes
B10: Rejected: bad_date | C10: 1
B11: Rejected: bad_price | C11: 1
B12: Rejected: exact_duplicate | C12: 26
B13: Rejected: order_id_conflict | C13: 1
B14: Rejected: unknown_region | C14: 1
B15: Rejected: zero_qty | C15: 1
B16: Adjustment: blank_segment_imputed | C16: 77
B17: Adjustment: discount_percent_scaled | C17: 0
B18: Adjustment: negative_qty_corrected | C18: 1
B19: Adjustment: order_id_conflict | C19: 1
B20: Adjustment: ship_days_cleared | C20: 1
B21: Adjustment: unknown_segment_imputed | C21: 0
